// class version 55.0 (55)
// access flags 0x21
public class modbat/bes/SimpleCounterBES {

  // compiled from: SimpleCounterBES.java

  // access flags 0x0
  I count

  // access flags 0x0
  Z flag

  // access flags 0x0
  I incrementBy

  // access flags 0x1
  public <init>()V
   L0
    LINENUMBER 3 L0
    ALOAD 0
    INVOKESPECIAL java/lang/Object.<init> ()V
   L1
    LINENUMBER 4 L1
    ALOAD 0
    ICONST_0
    PUTFIELD modbat/bes/SimpleCounterBES.count : I
   L2
    LINENUMBER 5 L2
    ALOAD 0
    ICONST_1
    PUTFIELD modbat/bes/SimpleCounterBES.flag : Z
   L3
    LINENUMBER 6 L3
    ALOAD 0
    ICONST_2
    PUTFIELD modbat/bes/SimpleCounterBES.incrementBy : I
    RETURN
   L4
    LOCALVARIABLE this Lmodbat/bes/SimpleCounterBES; L0 L4 0
    MAXSTACK = 2
    MAXLOCALS = 1

  // access flags 0x1
  public toggleSwitch()V
   L0
    LINENUMBER 10 L0
    ALOAD 0
    ALOAD 0
    GETFIELD modbat/bes/SimpleCounterBES.flag : Z
    POP
    GOTO L1
   L2
   FRAME FULL [] [java/lang/Throwable]
    NOP
    NOP
    NOP
    ATHROW
   L1
   FRAME FULL [modbat/bes/SimpleCounterBES] [modbat/bes/SimpleCounterBES]
    ICONST_0
    PUTFIELD modbat/bes/SimpleCounterBES.flag : Z
   L3
    LINENUMBER 11 L3
    RETURN
   L4
    LOCALVARIABLE this Lmodbat/bes/SimpleCounterBES; L0 L4 0
    MAXSTACK = 2
    MAXLOCALS = 1

  // access flags 0x1
  public inc()V
   L0
    LINENUMBER 14 L0
    ALOAD 0
    GETFIELD modbat/bes/SimpleCounterBES.flag : Z
    IFEQ L1
    ALOAD 0
    GETFIELD modbat/bes/SimpleCounterBES.incrementBy : I
    ICONST_1
    IF_ICMPNE L1
   L2
    LINENUMBER 15 L2
    ALOAD 0
    DUP
    GETFIELD modbat/bes/SimpleCounterBES.count : I
    ICONST_1
    IADD
    PUTFIELD modbat/bes/SimpleCounterBES.count : I
   L1
    LINENUMBER 17 L1
   FRAME FULL [modbat/bes/SimpleCounterBES] []
    RETURN
   L3
    LOCALVARIABLE this Lmodbat/bes/SimpleCounterBES; L0 L3 0
    MAXSTACK = 3
    MAXLOCALS = 1

  // access flags 0x1
  public inc2()V
   L0
    LINENUMBER 20 L0
    ALOAD 0
    DUP
    GETFIELD modbat/bes/SimpleCounterBES.count : I
    ALOAD 0
    GETFIELD modbat/bes/SimpleCounterBES.incrementBy : I
    IADD
    PUTFIELD modbat/bes/SimpleCounterBES.count : I
   L1
    LINENUMBER 21 L1
    RETURN
   L2
    LOCALVARIABLE this Lmodbat/bes/SimpleCounterBES; L0 L2 0
    MAXSTACK = 3
    MAXLOCALS = 1

  // access flags 0x1
  public getIncrementBy()I
   L0
    LINENUMBER 24 L0
    ALOAD 0
    GETFIELD modbat/bes/SimpleCounterBES.incrementBy : I
    IRETURN
   L1
    LOCALVARIABLE this Lmodbat/bes/SimpleCounterBES; L0 L1 0
    MAXSTACK = 1
    MAXLOCALS = 1

  // access flags 0x1
  public setIncrementBy(I)V
   L0
    LINENUMBER 28 L0
    ALOAD 0
    ILOAD 1
    PUTFIELD modbat/bes/SimpleCounterBES.incrementBy : I
   L1
    LINENUMBER 29 L1
    RETURN
   L2
    LOCALVARIABLE this Lmodbat/bes/SimpleCounterBES; L0 L2 0
    LOCALVARIABLE incrementBy I L0 L2 1
    MAXSTACK = 2
    MAXLOCALS = 2

  // access flags 0x1
  public value()I
   L0
    LINENUMBER 32 L0
    ALOAD 0
    GETFIELD modbat/bes/SimpleCounterBES.count : I
    IRETURN
   L1
    LOCALVARIABLE this Lmodbat/bes/SimpleCounterBES; L0 L1 0
    MAXSTACK = 1
    MAXLOCALS = 1

  // access flags 0x1
  public setValue(I)V
   L0
    LINENUMBER 36 L0
    ALOAD 0
    ILOAD 1
    PUTFIELD modbat/bes/SimpleCounterBES.count : I
   L1
    LINENUMBER 37 L1
    RETURN
   L2
    LOCALVARIABLE this Lmodbat/bes/SimpleCounterBES; L0 L2 0
    LOCALVARIABLE value I L0 L2 1
    MAXSTACK = 2
    MAXLOCALS = 2

  // access flags 0x9
  public static main([Ljava/lang/String;)V
   L0
    LINENUMBER 41 L0
    RETURN
   L1
    LOCALVARIABLE args [Ljava/lang/String; L0 L1 0
    MAXSTACK = 0
    MAXLOCALS = 1
}

