// class version 55.0 (55)
// access flags 0x21
public class modbat/bes/JavaNioSocketSUT {

  // compiled from: JavaNioSocketSUT.java
  NESTMEMBER modbat/bes/JavaNioSocketSUT$TestServer
  // access flags 0xA
  private static INNERCLASS modbat/bes/JavaNioSocketSUT$TestServer modbat/bes/JavaNioSocketSUT TestServer

  // access flags 0x8
  static I port

  // access flags 0x8
  static Lmodbat/bes/JavaNioSocketSUT$TestServer; server

  // access flags 0x0
  Ljava/nio/channels/SocketChannel; connection

  // access flags 0x0
  Z isConnected

  // access flags 0x0
  I n

  // access flags 0x1
  public <init>()V
   L0
    LINENUMBER 8 L0
    ALOAD 0
    INVOKESPECIAL java/lang/Object.<init> ()V
   L1
    LINENUMBER 70 L1
    ALOAD 0
    ACONST_NULL
    PUTFIELD modbat/bes/JavaNioSocketSUT.connection : Ljava/nio/channels/SocketChannel;
   L2
    LINENUMBER 71 L2
    ALOAD 0
    ICONST_0
    PUTFIELD modbat/bes/JavaNioSocketSUT.isConnected : Z
   L3
    LINENUMBER 72 L3
    ALOAD 0
    ICONST_0
    PUTFIELD modbat/bes/JavaNioSocketSUT.n : I
    RETURN
   L4
    LOCALVARIABLE this Lmodbat/bes/JavaNioSocketSUT; L0 L4 0
    MAXSTACK = 2
    MAXLOCALS = 1

  // access flags 0x9
  public static startServer()V throws java/io/IOException 
   L0
    LINENUMBER 61 L0
    GETSTATIC modbat/bes/JavaNioSocketSUT.server : Lmodbat/bes/JavaNioSocketSUT$TestServer;
    INVOKEVIRTUAL modbat/bes/JavaNioSocketSUT$TestServer.start ()V
   L1
    LINENUMBER 62 L1
    RETURN
    MAXSTACK = 1
    MAXLOCALS = 0

  // access flags 0x9
  public static shutdown()V
   L0
    LINENUMBER 66 L0
    GETSTATIC modbat/bes/JavaNioSocketSUT.server : Lmodbat/bes/JavaNioSocketSUT$TestServer;
    INVOKEVIRTUAL modbat/bes/JavaNioSocketSUT$TestServer.interrupt ()V
   L1
    LINENUMBER 67 L1
    RETURN
    MAXSTACK = 1
    MAXLOCALS = 0

  // access flags 0x1
  public cleanup()V throws java/io/IOException 
   L0
    LINENUMBER 75 L0
    ALOAD 0
    GETFIELD modbat/bes/JavaNioSocketSUT.connection : Ljava/nio/channels/SocketChannel;
    IFNULL L1
   L2
    LINENUMBER 76 L2
    ALOAD 0
    GETFIELD modbat/bes/JavaNioSocketSUT.connection : Ljava/nio/channels/SocketChannel;
    INVOKEVIRTUAL java/nio/channels/SocketChannel.close ()V
   L1
    LINENUMBER 78 L1
   FRAME FULL [modbat/bes/JavaNioSocketSUT] []
    RETURN
   L3
    LOCALVARIABLE this Lmodbat/bes/JavaNioSocketSUT; L0 L3 0
    MAXSTACK = 1
    MAXLOCALS = 1

  // access flags 0x1
  public connect(Ljava/nio/channels/SocketChannel;)Z throws java/nio/channels/ClosedChannelException java/nio/channels/AlreadyConnectedException java/nio/channels/ConnectionPendingException java/io/IOException 
   L0
    LINENUMBER 82 L0
    ALOAD 1
    NEW java/net/InetSocketAddress
    DUP
    LDC "localhost"
    GETSTATIC modbat/bes/JavaNioSocketSUT.port : I
    INVOKESPECIAL java/net/InetSocketAddress.<init> (Ljava/lang/String;I)V
    INVOKEVIRTUAL java/nio/channels/SocketChannel.connect (Ljava/net/SocketAddress;)Z
    IRETURN
   L1
    LOCALVARIABLE this Lmodbat/bes/JavaNioSocketSUT; L0 L1 0
    LOCALVARIABLE connection Ljava/nio/channels/SocketChannel; L0 L1 1
    MAXSTACK = 5
    MAXLOCALS = 2

  // access flags 0x1
  public readFrom(Ljava/nio/channels/SocketChannel;I)I throws java/nio/channels/ClosedChannelException java/nio/channels/NotYetConnectedException java/io/IOException 
   L0
    LINENUMBER 86 L0
    ICONST_1
    INVOKESTATIC java/nio/ByteBuffer.allocate (I)Ljava/nio/ByteBuffer;
    ASTORE 3
   L1
    LINENUMBER 89 L1
    ALOAD 1
    ALOAD 3
    INVOKEVIRTUAL java/nio/channels/SocketChannel.read (Ljava/nio/ByteBuffer;)I
    ISTORE 4
   L2
    LINENUMBER 90 L2
    ILOAD 2
    ICONST_2
    IF_ICMPGE L3
   L4
    LINENUMBER 91 L4
    ICONST_0
    ISTORE 5
   L5
    LINENUMBER 92 L5
    ALOAD 1
    INVOKEVIRTUAL java/nio/channels/SocketChannel.isBlocking ()Z
    POP
    GOTO L3
   L6
    LINENUMBER 93 L6
   FRAME FULL [] [java/lang/Throwable]
    NOP
    NOP
    ATHROW
   L3
    LINENUMBER 103 L3
   FRAME FULL [modbat/bes/JavaNioSocketSUT java/nio/channels/SocketChannel I java/nio/ByteBuffer I] []
    ILOAD 4
    IRETURN
   L7
    LOCALVARIABLE limit I L5 L3 5
    LOCALVARIABLE this Lmodbat/bes/JavaNioSocketSUT; L0 L7 0
    LOCALVARIABLE connection Ljava/nio/channels/SocketChannel; L0 L7 1
    LOCALVARIABLE n I L0 L7 2
    LOCALVARIABLE buf Ljava/nio/ByteBuffer; L1 L7 3
    LOCALVARIABLE l I L2 L7 4
    MAXSTACK = 2
    MAXLOCALS = 6

  // access flags 0x1
  public toggleBlocking(Ljava/nio/channels/SocketChannel;)V throws java/nio/channels/ClosedChannelException java/io/IOException 
   L0
    LINENUMBER 107 L0
    ALOAD 1
    ALOAD 1
    INVOKEVIRTUAL java/nio/channels/SocketChannel.isBlocking ()Z
    IFNE L1
    ICONST_1
    GOTO L2
   L1
   FRAME FULL [modbat/bes/JavaNioSocketSUT java/nio/channels/SocketChannel] [java/nio/channels/SocketChannel]
    ICONST_0
   L2
   FRAME FULL [modbat/bes/JavaNioSocketSUT java/nio/channels/SocketChannel] [java/nio/channels/SocketChannel I]
    INVOKEVIRTUAL java/nio/channels/SocketChannel.configureBlocking (Z)Ljava/nio/channels/SelectableChannel;
    POP
   L3
    LINENUMBER 108 L3
    RETURN
   L4
    LOCALVARIABLE this Lmodbat/bes/JavaNioSocketSUT; L0 L4 0
    LOCALVARIABLE connection Ljava/nio/channels/SocketChannel; L0 L4 1
    MAXSTACK = 2
    MAXLOCALS = 2

  // access flags 0x1
  public openChannel()V throws java/io/IOException 
   L0
    LINENUMBER 112 L0
    ALOAD 0
    INVOKESTATIC java/nio/channels/SocketChannel.open ()Ljava/nio/channels/SocketChannel;
    PUTFIELD modbat/bes/JavaNioSocketSUT.connection : Ljava/nio/channels/SocketChannel;
   L1
    LINENUMBER 113 L1
    RETURN
   L2
    LOCALVARIABLE this Lmodbat/bes/JavaNioSocketSUT; L0 L2 0
    MAXSTACK = 2
    MAXLOCALS = 1

  // access flags 0x1
  public toggleBlocking()V throws java/nio/channels/ClosedChannelException java/io/IOException 
   L0
    LINENUMBER 116 L0
    ALOAD 0
    ALOAD 0
    GETFIELD modbat/bes/JavaNioSocketSUT.connection : Ljava/nio/channels/SocketChannel;
    INVOKEVIRTUAL modbat/bes/JavaNioSocketSUT.toggleBlocking (Ljava/nio/channels/SocketChannel;)V
   L1
    LINENUMBER 117 L1
    RETURN
   L2
    LOCALVARIABLE this Lmodbat/bes/JavaNioSocketSUT; L0 L2 0
    MAXSTACK = 2
    MAXLOCALS = 1

  // access flags 0x1
  public isBlocking()Z
   L0
    LINENUMBER 120 L0
    ALOAD 0
    GETFIELD modbat/bes/JavaNioSocketSUT.connection : Ljava/nio/channels/SocketChannel;
    INVOKEVIRTUAL java/nio/channels/SocketChannel.isBlocking ()Z
    IRETURN
   L1
    LOCALVARIABLE this Lmodbat/bes/JavaNioSocketSUT; L0 L1 0
    MAXSTACK = 1
    MAXLOCALS = 1

  // access flags 0x1
  public sleep(I)V throws java/lang/InterruptedException 
   L0
    LINENUMBER 124 L0
    ILOAD 1
    I2L
    INVOKESTATIC java/lang/Thread.sleep (J)V
   L1
    LINENUMBER 125 L1
    RETURN
   L2
    LOCALVARIABLE this Lmodbat/bes/JavaNioSocketSUT; L0 L2 0
    LOCALVARIABLE x I L0 L2 1
    MAXSTACK = 2
    MAXLOCALS = 2

  // access flags 0x1
  public connectConnection()Z throws java/nio/channels/ClosedChannelException java/nio/channels/AlreadyConnectedException java/nio/channels/ConnectionPendingException java/io/IOException 
   L0
    LINENUMBER 128 L0
    ALOAD 0
    ALOAD 0
    GETFIELD modbat/bes/JavaNioSocketSUT.connection : Ljava/nio/channels/SocketChannel;
    INVOKEVIRTUAL modbat/bes/JavaNioSocketSUT.connect (Ljava/nio/channels/SocketChannel;)Z
    IRETURN
   L1
    LOCALVARIABLE this Lmodbat/bes/JavaNioSocketSUT; L0 L1 0
    MAXSTACK = 2
    MAXLOCALS = 1

  // access flags 0x1
  public finishConnect()Z throws java/nio/channels/ClosedChannelException java/nio/channels/NoConnectionPendingException java/io/IOException 
   L0
    LINENUMBER 141 L0
    ALOAD 0
    GETFIELD modbat/bes/JavaNioSocketSUT.connection : Ljava/nio/channels/SocketChannel;
    INVOKEVIRTUAL java/nio/channels/SocketChannel.finishConnect ()Z
    IRETURN
   L1
    LOCALVARIABLE this Lmodbat/bes/JavaNioSocketSUT; L0 L1 0
    MAXSTACK = 1
    MAXLOCALS = 1

  // access flags 0x1
  public readFrom()I throws java/nio/channels/ClosedChannelException java/nio/channels/NotYetConnectedException java/io/IOException 
   L0
    LINENUMBER 146 L0
    ALOAD 0
    ALOAD 0
    GETFIELD modbat/bes/JavaNioSocketSUT.connection : Ljava/nio/channels/SocketChannel;
    ALOAD 0
    GETFIELD modbat/bes/JavaNioSocketSUT.n : I
    INVOKEVIRTUAL modbat/bes/JavaNioSocketSUT.readFrom (Ljava/nio/channels/SocketChannel;I)I
    IRETURN
   L1
    LOCALVARIABLE this Lmodbat/bes/JavaNioSocketSUT; L0 L1 0
    MAXSTACK = 3
    MAXLOCALS = 1

  // access flags 0x1
  public maybeIncrementN(I)V throws java/nio/channels/ClosedChannelException java/nio/channels/NotYetConnectedException java/io/IOException 
   L0
    LINENUMBER 151 L0
    ILOAD 1
    IFLE L1
   L2
    LINENUMBER 152 L2
    ALOAD 0
    ALOAD 0
    GETFIELD modbat/bes/JavaNioSocketSUT.n : I
    ILOAD 1
    IADD
    PUTFIELD modbat/bes/JavaNioSocketSUT.n : I
   L1
    LINENUMBER 154 L1
   FRAME FULL [modbat/bes/JavaNioSocketSUT I] []
    RETURN
   L3
    LOCALVARIABLE this Lmodbat/bes/JavaNioSocketSUT; L0 L3 0
    LOCALVARIABLE l I L0 L3 1
    MAXSTACK = 3
    MAXLOCALS = 2

  // access flags 0x1
  public closeConnection()V throws java/io/IOException 
   L0
    LINENUMBER 157 L0
    ALOAD 0
    GETFIELD modbat/bes/JavaNioSocketSUT.connection : Ljava/nio/channels/SocketChannel;
    INVOKEVIRTUAL java/nio/channels/SocketChannel.close ()V
   L1
    LINENUMBER 158 L1
    RETURN
   L2
    LOCALVARIABLE this Lmodbat/bes/JavaNioSocketSUT; L0 L2 0
    MAXSTACK = 1
    MAXLOCALS = 1

  // access flags 0x1
  public getConnection()Ljava/nio/channels/SocketChannel;
   L0
    LINENUMBER 165 L0
    ALOAD 0
    GETFIELD modbat/bes/JavaNioSocketSUT.connection : Ljava/nio/channels/SocketChannel;
    ARETURN
   L1
    LOCALVARIABLE this Lmodbat/bes/JavaNioSocketSUT; L0 L1 0
    MAXSTACK = 1
    MAXLOCALS = 1

  // access flags 0x1
  public isConnected()Z
   L0
    LINENUMBER 169 L0
    ALOAD 0
    GETFIELD modbat/bes/JavaNioSocketSUT.isConnected : Z
    IRETURN
   L1
    LOCALVARIABLE this Lmodbat/bes/JavaNioSocketSUT; L0 L1 0
    MAXSTACK = 1
    MAXLOCALS = 1

  // access flags 0x1
  public getN()I
   L0
    LINENUMBER 173 L0
    ALOAD 0
    GETFIELD modbat/bes/JavaNioSocketSUT.n : I
    IRETURN
   L1
    LOCALVARIABLE this Lmodbat/bes/JavaNioSocketSUT; L0 L1 0
    MAXSTACK = 1
    MAXLOCALS = 1

  // access flags 0x1
  public setConnected(Z)V
   L0
    LINENUMBER 181 L0
    ALOAD 0
    ILOAD 1
    PUTFIELD modbat/bes/JavaNioSocketSUT.isConnected : Z
   L1
    LINENUMBER 182 L1
    RETURN
   L2
    LOCALVARIABLE this Lmodbat/bes/JavaNioSocketSUT; L0 L2 0
    LOCALVARIABLE connected Z L0 L2 1
    MAXSTACK = 2
    MAXLOCALS = 2

  // access flags 0x9
  public static main([Ljava/lang/String;)V
   L0
    LINENUMBER 185 L0
    RETURN
   L1
    LOCALVARIABLE args [Ljava/lang/String; L0 L1 0
    MAXSTACK = 0
    MAXLOCALS = 1

  // access flags 0x8
  static <clinit>()V
   L0
    LINENUMBER 10 L0
    ICONST_0
    PUTSTATIC modbat/bes/JavaNioSocketSUT.port : I
   L1
    LINENUMBER 11 L1
    ACONST_NULL
    PUTSTATIC modbat/bes/JavaNioSocketSUT.server : Lmodbat/bes/JavaNioSocketSUT$TestServer;
    RETURN
    MAXSTACK = 1
    MAXLOCALS = 0
}

