// class version 55.0 (55)
// access flags 0x21
public class modbat/bes/JavaNioServerSocket3SUT extends java/lang/Thread {

  // compiled from: JavaNioServerSocket3SUT.java
  NESTMEMBER modbat/bes/JavaNioServerSocket3SUT$TestClient
  // access flags 0x2
  private INNERCLASS modbat/bes/JavaNioServerSocket3SUT$TestClient modbat/bes/JavaNioServerSocket3SUT TestClient

  // access flags 0x2
  private Ljava/nio/channels/ServerSocketChannel; ch

  // access flags 0x2
  private Ljava/nio/channels/SocketChannel; connection

  // access flags 0x2
  private Lmodbat/bes/JavaNioServerSocket3SUT$TestClient; client

  // access flags 0x2
  private I port

  // access flags 0x2
  private I count

  // access flags 0x1
  public <init>()V
   L0
    LINENUMBER 11 L0
    ALOAD 0
    INVOKESPECIAL java/lang/Thread.<init> ()V
   L1
    LINENUMBER 13 L1
    ALOAD 0
    ACONST_NULL
    PUTFIELD modbat/bes/JavaNioServerSocket3SUT.ch : Ljava/nio/channels/ServerSocketChannel;
   L2
    LINENUMBER 14 L2
    ALOAD 0
    ACONST_NULL
    PUTFIELD modbat/bes/JavaNioServerSocket3SUT.connection : Ljava/nio/channels/SocketChannel;
   L3
    LINENUMBER 15 L3
    ALOAD 0
    ACONST_NULL
    PUTFIELD modbat/bes/JavaNioServerSocket3SUT.client : Lmodbat/bes/JavaNioServerSocket3SUT$TestClient;
   L4
    LINENUMBER 16 L4
    ALOAD 0
    ICONST_0
    PUTFIELD modbat/bes/JavaNioServerSocket3SUT.port : I
   L5
    LINENUMBER 17 L5
    ALOAD 0
    ICONST_0
    PUTFIELD modbat/bes/JavaNioServerSocket3SUT.count : I
    RETURN
   L6
    LOCALVARIABLE this Lmodbat/bes/JavaNioServerSocket3SUT; L0 L6 0
    MAXSTACK = 2
    MAXLOCALS = 1

  // access flags 0x1
  public toggleBlocking()V throws java/io/IOException 
   L0
    LINENUMBER 50 L0
    ALOAD 0
    ALOAD 0
    GETFIELD modbat/bes/JavaNioServerSocket3SUT.ch : Ljava/nio/channels/ServerSocketChannel;
    INVOKEVIRTUAL modbat/bes/JavaNioServerSocket3SUT.toggleBlocking (Ljava/nio/channels/ServerSocketChannel;)V
   L1
    LINENUMBER 51 L1
    RETURN
   L2
    LOCALVARIABLE this Lmodbat/bes/JavaNioServerSocket3SUT; L0 L2 0
    MAXSTACK = 2
    MAXLOCALS = 1

  // access flags 0x1
  public toggleBlocking(Ljava/nio/channels/ServerSocketChannel;)V throws java/io/IOException 
   L0
    LINENUMBER 54 L0
    ALOAD 1
    ALOAD 1
    INVOKEVIRTUAL java/nio/channels/ServerSocketChannel.isBlocking ()Z
    IFNE L1
    ICONST_1
    GOTO L2
   L1
   FRAME FULL [modbat/bes/JavaNioServerSocket3SUT java/nio/channels/ServerSocketChannel] [java/nio/channels/ServerSocketChannel]
    ICONST_0
   L2
   FRAME FULL [modbat/bes/JavaNioServerSocket3SUT java/nio/channels/ServerSocketChannel] [java/nio/channels/ServerSocketChannel I]
    INVOKEVIRTUAL java/nio/channels/ServerSocketChannel.configureBlocking (Z)Ljava/nio/channels/SelectableChannel;
    POP
   L3
    LINENUMBER 55 L3
    RETURN
   L4
    LOCALVARIABLE this Lmodbat/bes/JavaNioServerSocket3SUT; L0 L4 0
    LOCALVARIABLE ch Ljava/nio/channels/ServerSocketChannel; L0 L4 1
    MAXSTACK = 2
    MAXLOCALS = 2

  // access flags 0x1
  public cleanup()V throws java/io/IOException 
   L0
    LINENUMBER 59 L0
    ALOAD 0
    GETFIELD modbat/bes/JavaNioServerSocket3SUT.connection : Ljava/nio/channels/SocketChannel;
    IFNULL L1
   L2
    LINENUMBER 60 L2
    ALOAD 0
    GETFIELD modbat/bes/JavaNioServerSocket3SUT.connection : Ljava/nio/channels/SocketChannel;
    INVOKEVIRTUAL java/nio/channels/SocketChannel.close ()V
   L3
    LINENUMBER 61 L3
    ALOAD 0
    ACONST_NULL
    PUTFIELD modbat/bes/JavaNioServerSocket3SUT.connection : Ljava/nio/channels/SocketChannel;
   L1
    LINENUMBER 63 L1
   FRAME FULL [modbat/bes/JavaNioServerSocket3SUT] []
    ALOAD 0
    GETFIELD modbat/bes/JavaNioServerSocket3SUT.ch : Ljava/nio/channels/ServerSocketChannel;
    IFNULL L4
   L5
    LINENUMBER 64 L5
    ALOAD 0
    GETFIELD modbat/bes/JavaNioServerSocket3SUT.ch : Ljava/nio/channels/ServerSocketChannel;
    INVOKEVIRTUAL java/nio/channels/ServerSocketChannel.close ()V
   L6
    LINENUMBER 65 L6
    ALOAD 0
    ACONST_NULL
    PUTFIELD modbat/bes/JavaNioServerSocket3SUT.ch : Ljava/nio/channels/ServerSocketChannel;
   L4
    LINENUMBER 67 L4
   FRAME FULL [modbat/bes/JavaNioServerSocket3SUT] []
    ALOAD 0
    GETFIELD modbat/bes/JavaNioServerSocket3SUT.client : Lmodbat/bes/JavaNioServerSocket3SUT$TestClient;
    IFNULL L7
   L8
    LINENUMBER 68 L8
    ALOAD 0
    GETFIELD modbat/bes/JavaNioServerSocket3SUT.client : Lmodbat/bes/JavaNioServerSocket3SUT$TestClient;
    INVOKEVIRTUAL modbat/bes/JavaNioServerSocket3SUT$TestClient.interrupt ()V
   L9
    LINENUMBER 69 L9
    ALOAD 0
    ACONST_NULL
    PUTFIELD modbat/bes/JavaNioServerSocket3SUT.client : Lmodbat/bes/JavaNioServerSocket3SUT$TestClient;
   L7
    LINENUMBER 71 L7
   FRAME FULL [modbat/bes/JavaNioServerSocket3SUT] []
    RETURN
   L10
    LOCALVARIABLE this Lmodbat/bes/JavaNioServerSocket3SUT; L0 L10 0
    MAXSTACK = 2
    MAXLOCALS = 1

  // access flags 0x1
  public readFrom()I throws java/io/IOException 
   L0
    LINENUMBER 74 L0
    ALOAD 0
    ALOAD 0
    GETFIELD modbat/bes/JavaNioServerSocket3SUT.connection : Ljava/nio/channels/SocketChannel;
    INVOKEVIRTUAL modbat/bes/JavaNioServerSocket3SUT.readFrom (Ljava/nio/channels/SocketChannel;)I
    IRETURN
   L1
    LOCALVARIABLE this Lmodbat/bes/JavaNioServerSocket3SUT; L0 L1 0
    MAXSTACK = 2
    MAXLOCALS = 1

  // access flags 0x1
  public readFrom(Ljava/nio/channels/SocketChannel;)I throws java/io/IOException 
   L0
    LINENUMBER 78 L0
    ICONST_1
    INVOKESTATIC java/nio/ByteBuffer.allocate (I)Ljava/nio/ByteBuffer;
    ASTORE 2
   L1
    LINENUMBER 79 L1
    ALOAD 1
    ALOAD 2
    INVOKEVIRTUAL java/nio/channels/SocketChannel.read (Ljava/nio/ByteBuffer;)I
    IRETURN
   L2
    LOCALVARIABLE this Lmodbat/bes/JavaNioServerSocket3SUT; L0 L2 0
    LOCALVARIABLE ch Ljava/nio/channels/SocketChannel; L0 L2 1
    LOCALVARIABLE buf Ljava/nio/ByteBuffer; L1 L2 2
    MAXSTACK = 2
    MAXLOCALS = 3

  // access flags 0x1
  public startClient()V
   L0
    LINENUMBER 83 L0
    ALOAD 0
    NEW modbat/bes/JavaNioServerSocket3SUT$TestClient
    DUP
    ALOAD 0
    INVOKESPECIAL modbat/bes/JavaNioServerSocket3SUT$TestClient.<init> (Lmodbat/bes/JavaNioServerSocket3SUT;)V
    PUTFIELD modbat/bes/JavaNioServerSocket3SUT.client : Lmodbat/bes/JavaNioServerSocket3SUT$TestClient;
   L1
    LINENUMBER 85 L1
    ALOAD 0
    GETFIELD modbat/bes/JavaNioServerSocket3SUT.client : Lmodbat/bes/JavaNioServerSocket3SUT$TestClient;
    INVOKEVIRTUAL modbat/bes/JavaNioServerSocket3SUT$TestClient.run ()V
   L2
    LINENUMBER 87 L2
    ALOAD 0
    ICONST_0
    PUTFIELD modbat/bes/JavaNioServerSocket3SUT.count : I
   L3
    LINENUMBER 88 L3
    RETURN
   L4
    LOCALVARIABLE this Lmodbat/bes/JavaNioServerSocket3SUT; L0 L4 0
    MAXSTACK = 4
    MAXLOCALS = 1

  // access flags 0x1
  public openChannel()V throws java/io/IOException 
   L0
    LINENUMBER 92 L0
    ALOAD 0
    INVOKESTATIC java/nio/channels/ServerSocketChannel.open ()Ljava/nio/channels/ServerSocketChannel;
    PUTFIELD modbat/bes/JavaNioServerSocket3SUT.ch : Ljava/nio/channels/ServerSocketChannel;
   L1
    LINENUMBER 93 L1
    RETURN
   L2
    LOCALVARIABLE this Lmodbat/bes/JavaNioServerSocket3SUT; L0 L2 0
    MAXSTACK = 2
    MAXLOCALS = 1

  // access flags 0x1
  public bindAndSetPort()V throws java/io/IOException 
   L0
    LINENUMBER 97 L0
    ALOAD 0
    GETFIELD modbat/bes/JavaNioServerSocket3SUT.ch : Ljava/nio/channels/ServerSocketChannel;
    INVOKEVIRTUAL java/nio/channels/ServerSocketChannel.socket ()Ljava/net/ServerSocket;
    NEW java/net/InetSocketAddress
    DUP
    LDC "localhost"
    ICONST_0
    INVOKESPECIAL java/net/InetSocketAddress.<init> (Ljava/lang/String;I)V
    INVOKEVIRTUAL java/net/ServerSocket.bind (Ljava/net/SocketAddress;)V
   L1
    LINENUMBER 98 L1
    ALOAD 0
    ALOAD 0
    GETFIELD modbat/bes/JavaNioServerSocket3SUT.ch : Ljava/nio/channels/ServerSocketChannel;
    INVOKEVIRTUAL java/nio/channels/ServerSocketChannel.socket ()Ljava/net/ServerSocket;
    INVOKEVIRTUAL java/net/ServerSocket.getLocalPort ()I
    PUTFIELD modbat/bes/JavaNioServerSocket3SUT.port : I
   L2
    LINENUMBER 99 L2
    RETURN
   L3
    LOCALVARIABLE this Lmodbat/bes/JavaNioServerSocket3SUT; L0 L3 0
    MAXSTACK = 5
    MAXLOCALS = 1

  // access flags 0x1
  public onlyBind()V throws java/io/IOException 
   L0
    LINENUMBER 102 L0
    ALOAD 0
    GETFIELD modbat/bes/JavaNioServerSocket3SUT.ch : Ljava/nio/channels/ServerSocketChannel;
    INVOKEVIRTUAL java/nio/channels/ServerSocketChannel.socket ()Ljava/net/ServerSocket;
    NEW java/net/InetSocketAddress
    DUP
    LDC "localhost"
    ICONST_0
    INVOKESPECIAL java/net/InetSocketAddress.<init> (Ljava/lang/String;I)V
    INVOKEVIRTUAL java/net/ServerSocket.bind (Ljava/net/SocketAddress;)V
   L1
    LINENUMBER 103 L1
    RETURN
   L2
    LOCALVARIABLE this Lmodbat/bes/JavaNioServerSocket3SUT; L0 L2 0
    MAXSTACK = 5
    MAXLOCALS = 1

  // access flags 0x1
  public acceptChannel()V throws java/nio/channels/NotYetBoundException java/io/IOException 
   L0
    LINENUMBER 106 L0
    ALOAD 0
    ALOAD 0
    GETFIELD modbat/bes/JavaNioServerSocket3SUT.ch : Ljava/nio/channels/ServerSocketChannel;
    INVOKEVIRTUAL java/nio/channels/ServerSocketChannel.accept ()Ljava/nio/channels/SocketChannel;
    PUTFIELD modbat/bes/JavaNioServerSocket3SUT.connection : Ljava/nio/channels/SocketChannel;
   L1
    LINENUMBER 107 L1
    RETURN
   L2
    LOCALVARIABLE this Lmodbat/bes/JavaNioServerSocket3SUT; L0 L2 0
    MAXSTACK = 2
    MAXLOCALS = 1

  // access flags 0x1
  public isBlocking()Z
   L0
    LINENUMBER 110 L0
    ALOAD 0
    GETFIELD modbat/bes/JavaNioServerSocket3SUT.ch : Ljava/nio/channels/ServerSocketChannel;
    INVOKEVIRTUAL java/nio/channels/ServerSocketChannel.isBlocking ()Z
    IRETURN
   L1
    LOCALVARIABLE this Lmodbat/bes/JavaNioServerSocket3SUT; L0 L1 0
    MAXSTACK = 1
    MAXLOCALS = 1

  // access flags 0x1
  public closeConnection()V throws java/io/IOException 
   L0
    LINENUMBER 115 L0
    ALOAD 0
    GETFIELD modbat/bes/JavaNioServerSocket3SUT.connection : Ljava/nio/channels/SocketChannel;
    INVOKEVIRTUAL java/nio/channels/SocketChannel.close ()V
   L1
    LINENUMBER 116 L1
    RETURN
   L2
    LOCALVARIABLE this Lmodbat/bes/JavaNioServerSocket3SUT; L0 L2 0
    MAXSTACK = 1
    MAXLOCALS = 1

  // access flags 0x1
  public closeChannel()V throws java/io/IOException 
   L0
    LINENUMBER 119 L0
    ALOAD 0
    GETFIELD modbat/bes/JavaNioServerSocket3SUT.ch : Ljava/nio/channels/ServerSocketChannel;
    INVOKEVIRTUAL java/nio/channels/ServerSocketChannel.close ()V
   L1
    LINENUMBER 120 L1
    RETURN
   L2
    LOCALVARIABLE this Lmodbat/bes/JavaNioServerSocket3SUT; L0 L2 0
    MAXSTACK = 1
    MAXLOCALS = 1

  // access flags 0x1
  public interruptClient()V
   L0
    LINENUMBER 124 L0
    ALOAD 0
    GETFIELD modbat/bes/JavaNioServerSocket3SUT.client : Lmodbat/bes/JavaNioServerSocket3SUT$TestClient;
    INVOKEVIRTUAL modbat/bes/JavaNioServerSocket3SUT$TestClient.interrupt ()V
   L1
    LINENUMBER 125 L1
    RETURN
   L2
    LOCALVARIABLE this Lmodbat/bes/JavaNioServerSocket3SUT; L0 L2 0
    MAXSTACK = 1
    MAXLOCALS = 1

  // access flags 0x1
  public incrementCountByOne()V
   L0
    LINENUMBER 128 L0
    ALOAD 0
    DUP
    GETFIELD modbat/bes/JavaNioServerSocket3SUT.count : I
    ICONST_1
    IADD
    PUTFIELD modbat/bes/JavaNioServerSocket3SUT.count : I
   L1
    LINENUMBER 129 L1
    RETURN
   L2
    LOCALVARIABLE this Lmodbat/bes/JavaNioServerSocket3SUT; L0 L2 0
    MAXSTACK = 3
    MAXLOCALS = 1

  // access flags 0x1
  public getCh()Ljava/nio/channels/ServerSocketChannel;
   L0
    LINENUMBER 134 L0
    ALOAD 0
    GETFIELD modbat/bes/JavaNioServerSocket3SUT.ch : Ljava/nio/channels/ServerSocketChannel;
    ARETURN
   L1
    LOCALVARIABLE this Lmodbat/bes/JavaNioServerSocket3SUT; L0 L1 0
    MAXSTACK = 1
    MAXLOCALS = 1

  // access flags 0x1
  public getConnection()Ljava/nio/channels/SocketChannel;
   L0
    LINENUMBER 138 L0
    ALOAD 0
    GETFIELD modbat/bes/JavaNioServerSocket3SUT.connection : Ljava/nio/channels/SocketChannel;
    ARETURN
   L1
    LOCALVARIABLE this Lmodbat/bes/JavaNioServerSocket3SUT; L0 L1 0
    MAXSTACK = 1
    MAXLOCALS = 1

  // access flags 0x1
  public getClient()Lmodbat/bes/JavaNioServerSocket3SUT$TestClient;
   L0
    LINENUMBER 142 L0
    ALOAD 0
    GETFIELD modbat/bes/JavaNioServerSocket3SUT.client : Lmodbat/bes/JavaNioServerSocket3SUT$TestClient;
    ARETURN
   L1
    LOCALVARIABLE this Lmodbat/bes/JavaNioServerSocket3SUT; L0 L1 0
    MAXSTACK = 1
    MAXLOCALS = 1

  // access flags 0x1
  public getPort()I
   L0
    LINENUMBER 146 L0
    ALOAD 0
    GETFIELD modbat/bes/JavaNioServerSocket3SUT.port : I
    IRETURN
   L1
    LOCALVARIABLE this Lmodbat/bes/JavaNioServerSocket3SUT; L0 L1 0
    MAXSTACK = 1
    MAXLOCALS = 1

  // access flags 0x1
  public getCount()I
   L0
    LINENUMBER 150 L0
    ALOAD 0
    GETFIELD modbat/bes/JavaNioServerSocket3SUT.count : I
    POP
    ICONST_0
    IRETURN
   L1
    LOCALVARIABLE this Lmodbat/bes/JavaNioServerSocket3SUT; L0 L1 0
    MAXSTACK = 1
    MAXLOCALS = 1

  // access flags 0x1
  public setConnection(Ljava/nio/channels/SocketChannel;)V
   L0
    LINENUMBER 156 L0
    ALOAD 0
    ALOAD 1
    PUTFIELD modbat/bes/JavaNioServerSocket3SUT.connection : Ljava/nio/channels/SocketChannel;
   L1
    LINENUMBER 157 L1
    RETURN
   L2
    LOCALVARIABLE this Lmodbat/bes/JavaNioServerSocket3SUT; L0 L2 0
    LOCALVARIABLE connection Ljava/nio/channels/SocketChannel; L0 L2 1
    MAXSTACK = 2
    MAXLOCALS = 2

  // access flags 0x1
  public setClient(Lmodbat/bes/JavaNioServerSocket3SUT$TestClient;)V
   L0
    LINENUMBER 160 L0
    ALOAD 0
    ALOAD 1
    PUTFIELD modbat/bes/JavaNioServerSocket3SUT.client : Lmodbat/bes/JavaNioServerSocket3SUT$TestClient;
   L1
    LINENUMBER 161 L1
    RETURN
   L2
    LOCALVARIABLE this Lmodbat/bes/JavaNioServerSocket3SUT; L0 L2 0
    LOCALVARIABLE client Lmodbat/bes/JavaNioServerSocket3SUT$TestClient; L0 L2 1
    MAXSTACK = 2
    MAXLOCALS = 2

  // access flags 0x9
  public static main([Ljava/lang/String;)V
   L0
    LINENUMBER 165 L0
    RETURN
   L1
    LOCALVARIABLE args [Ljava/lang/String; L0 L1 0
    MAXSTACK = 0
    MAXLOCALS = 1
}

