// class version 55.0 (55)
// access flags 0x21
// signature <E:Ljava/lang/Object;>Ljava/util/AbstractSequentialList<TE;>;Ljava/util/List<TE;>;Ljava/util/Deque<TE;>;Ljava/lang/Cloneable;Ljava/io/Serializable;
// declaration: modbat/bes/linkedlist/LinkedList<E> extends java.util.AbstractSequentialList<E> implements java.util.List<E>, java.util.Deque<E>, java.lang.Cloneable, java.io.Serializable
public class modbat/bes/linkedlist/LinkedList extends java/util/AbstractSequentialList implements java/util/List java/util/Deque java/lang/Cloneable java/io/Serializable {

  // compiled from: LinkedList.java
  NESTMEMBER modbat/bes/linkedlist/LinkedList$DescendingIterator
  NESTMEMBER modbat/bes/linkedlist/LinkedList$Node
  NESTMEMBER modbat/bes/linkedlist/LinkedList$ListItr
  // access flags 0x2
  private INNERCLASS modbat/bes/linkedlist/LinkedList$DescendingIterator modbat/bes/linkedlist/LinkedList DescendingIterator
  // access flags 0xA
  private static INNERCLASS modbat/bes/linkedlist/LinkedList$Node modbat/bes/linkedlist/LinkedList Node
  // access flags 0x2
  private INNERCLASS modbat/bes/linkedlist/LinkedList$ListItr modbat/bes/linkedlist/LinkedList ListItr
  // access flags 0x19
  public final static INNERCLASS java/lang/invoke/MethodHandles$Lookup java/lang/invoke/MethodHandles Lookup

  // access flags 0x80
  transient I size

  // access flags 0x80
  // signature Lmodbat/bes/linkedlist/LinkedList$Node<TE;>;
  // declaration: first extends modbat.bes.linkedlist.LinkedList$Node<E>
  transient Lmodbat/bes/linkedlist/LinkedList$Node; first

  // access flags 0x80
  // signature Lmodbat/bes/linkedlist/LinkedList$Node<TE;>;
  // declaration: last extends modbat.bes.linkedlist.LinkedList$Node<E>
  transient Lmodbat/bes/linkedlist/LinkedList$Node; last

  // access flags 0x1A
  private final static J serialVersionUID = 876323262645176354

  // access flags 0x1
  public <init>()V
   L0
    LINENUMBER 115 L0
    ALOAD 0
    INVOKESPECIAL java/util/AbstractSequentialList.<init> ()V
   L1
    LINENUMBER 96 L1
    ALOAD 0
    ICONST_0
    PUTFIELD modbat/bes/linkedlist/LinkedList.size : I
   L2
    LINENUMBER 116 L2
    RETURN
   L3
    LOCALVARIABLE this Lmodbat/bes/linkedlist/LinkedList; L0 L3 0
    // signature Lmodbat/bes/linkedlist/LinkedList<TE;>;
    // declaration: this extends modbat.bes.linkedlist.LinkedList<E>
    MAXSTACK = 2
    MAXLOCALS = 1

  // access flags 0x1
  // signature (Ljava/util/Collection<+TE;>;)V
  // declaration: void <init>(java.util.Collection<? extends E>)
  public <init>(Ljava/util/Collection;)V
   L0
    LINENUMBER 127 L0
    ALOAD 0
    INVOKESPECIAL modbat/bes/linkedlist/LinkedList.<init> ()V
   L1
    LINENUMBER 128 L1
    ALOAD 0
    ALOAD 1
    INVOKEVIRTUAL modbat/bes/linkedlist/LinkedList.addAll (Ljava/util/Collection;)Z
    POP
   L2
    LINENUMBER 129 L2
    RETURN
   L3
    LOCALVARIABLE this Lmodbat/bes/linkedlist/LinkedList; L0 L3 0
    // signature Lmodbat/bes/linkedlist/LinkedList<TE;>;
    // declaration: this extends modbat.bes.linkedlist.LinkedList<E>
    LOCALVARIABLE c Ljava/util/Collection; L0 L3 1
    // signature Ljava/util/Collection<+TE;>;
    // declaration: c extends java.util.Collection<? extends E>
    MAXSTACK = 2
    MAXLOCALS = 2

  // access flags 0x2
  // signature (TE;)V
  // declaration: void linkFirst(E)
  private linkFirst(Ljava/lang/Object;)V
   L0
    LINENUMBER 135 L0
    ALOAD 0
    GETFIELD modbat/bes/linkedlist/LinkedList.first : Lmodbat/bes/linkedlist/LinkedList$Node;
    ASTORE 2
   L1
    LINENUMBER 136 L1
    NEW modbat/bes/linkedlist/LinkedList$Node
    DUP
    ACONST_NULL
    ALOAD 1
    ALOAD 2
    INVOKESPECIAL modbat/bes/linkedlist/LinkedList$Node.<init> (Lmodbat/bes/linkedlist/LinkedList$Node;Ljava/lang/Object;Lmodbat/bes/linkedlist/LinkedList$Node;)V
    ASTORE 3
   L2
    LINENUMBER 137 L2
    ALOAD 0
    ALOAD 3
    PUTFIELD modbat/bes/linkedlist/LinkedList.first : Lmodbat/bes/linkedlist/LinkedList$Node;
   L3
    LINENUMBER 138 L3
    ALOAD 2
    IFNONNULL L4
   L5
    LINENUMBER 139 L5
    ALOAD 0
    ALOAD 3
    PUTFIELD modbat/bes/linkedlist/LinkedList.last : Lmodbat/bes/linkedlist/LinkedList$Node;
    GOTO L6
   L4
    LINENUMBER 141 L4
   FRAME FULL [modbat/bes/linkedlist/LinkedList java/lang/Object modbat/bes/linkedlist/LinkedList$Node modbat/bes/linkedlist/LinkedList$Node] []
    ALOAD 2
    ALOAD 3
    PUTFIELD modbat/bes/linkedlist/LinkedList$Node.prev : Lmodbat/bes/linkedlist/LinkedList$Node;
   L6
    LINENUMBER 142 L6
   FRAME FULL [modbat/bes/linkedlist/LinkedList java/lang/Object modbat/bes/linkedlist/LinkedList$Node modbat/bes/linkedlist/LinkedList$Node] []
    ALOAD 0
    DUP
    GETFIELD modbat/bes/linkedlist/LinkedList.size : I
    ICONST_1
    IADD
    PUTFIELD modbat/bes/linkedlist/LinkedList.size : I
   L7
    LINENUMBER 143 L7
    ALOAD 0
    DUP
    GETFIELD modbat/bes/linkedlist/LinkedList.modCount : I
    ICONST_1
    IADD
    PUTFIELD modbat/bes/linkedlist/LinkedList.modCount : I
   L8
    LINENUMBER 144 L8
    RETURN
   L9
    LOCALVARIABLE this Lmodbat/bes/linkedlist/LinkedList; L0 L9 0
    // signature Lmodbat/bes/linkedlist/LinkedList<TE;>;
    // declaration: this extends modbat.bes.linkedlist.LinkedList<E>
    LOCALVARIABLE e Ljava/lang/Object; L0 L9 1
    // signature TE;
    // declaration: e extends E
    LOCALVARIABLE f Lmodbat/bes/linkedlist/LinkedList$Node; L1 L9 2
    // signature Lmodbat/bes/linkedlist/LinkedList$Node<TE;>;
    // declaration: f extends modbat.bes.linkedlist.LinkedList$Node<E>
    LOCALVARIABLE newNode Lmodbat/bes/linkedlist/LinkedList$Node; L2 L9 3
    // signature Lmodbat/bes/linkedlist/LinkedList$Node<TE;>;
    // declaration: newNode extends modbat.bes.linkedlist.LinkedList$Node<E>
    MAXSTACK = 5
    MAXLOCALS = 4

  // access flags 0x0
  // signature (TE;)V
  // declaration: void linkLast(E)
  linkLast(Ljava/lang/Object;)V
   L0
    LINENUMBER 150 L0
    ALOAD 0
    GETFIELD modbat/bes/linkedlist/LinkedList.last : Lmodbat/bes/linkedlist/LinkedList$Node;
    ASTORE 2
   L1
    LINENUMBER 151 L1
    NEW modbat/bes/linkedlist/LinkedList$Node
    DUP
    ALOAD 2
    ALOAD 1
    ACONST_NULL
    INVOKESPECIAL modbat/bes/linkedlist/LinkedList$Node.<init> (Lmodbat/bes/linkedlist/LinkedList$Node;Ljava/lang/Object;Lmodbat/bes/linkedlist/LinkedList$Node;)V
    ASTORE 3
   L2
    LINENUMBER 152 L2
    ALOAD 0
    ALOAD 3
    PUTFIELD modbat/bes/linkedlist/LinkedList.last : Lmodbat/bes/linkedlist/LinkedList$Node;
   L3
    LINENUMBER 153 L3
    ALOAD 2
    IFNONNULL L4
   L5
    LINENUMBER 154 L5
    ALOAD 0
    ALOAD 3
    PUTFIELD modbat/bes/linkedlist/LinkedList.first : Lmodbat/bes/linkedlist/LinkedList$Node;
    GOTO L6
   L4
    LINENUMBER 156 L4
   FRAME FULL [modbat/bes/linkedlist/LinkedList java/lang/Object modbat/bes/linkedlist/LinkedList$Node modbat/bes/linkedlist/LinkedList$Node] []
    ALOAD 2
    ALOAD 3
    PUTFIELD modbat/bes/linkedlist/LinkedList$Node.next : Lmodbat/bes/linkedlist/LinkedList$Node;
   L6
    LINENUMBER 157 L6
   FRAME FULL [modbat/bes/linkedlist/LinkedList java/lang/Object modbat/bes/linkedlist/LinkedList$Node modbat/bes/linkedlist/LinkedList$Node] []
    ALOAD 0
    DUP
    GETFIELD modbat/bes/linkedlist/LinkedList.size : I
    ICONST_1
    IADD
    PUTFIELD modbat/bes/linkedlist/LinkedList.size : I
   L7
    LINENUMBER 158 L7
    ALOAD 0
    DUP
    GETFIELD modbat/bes/linkedlist/LinkedList.modCount : I
    ICONST_1
    IADD
    PUTFIELD modbat/bes/linkedlist/LinkedList.modCount : I
   L8
    LINENUMBER 159 L8
    RETURN
   L9
    LOCALVARIABLE this Lmodbat/bes/linkedlist/LinkedList; L0 L9 0
    // signature Lmodbat/bes/linkedlist/LinkedList<TE;>;
    // declaration: this extends modbat.bes.linkedlist.LinkedList<E>
    LOCALVARIABLE e Ljava/lang/Object; L0 L9 1
    // signature TE;
    // declaration: e extends E
    LOCALVARIABLE l Lmodbat/bes/linkedlist/LinkedList$Node; L1 L9 2
    // signature Lmodbat/bes/linkedlist/LinkedList$Node<TE;>;
    // declaration: l extends modbat.bes.linkedlist.LinkedList$Node<E>
    LOCALVARIABLE newNode Lmodbat/bes/linkedlist/LinkedList$Node; L2 L9 3
    // signature Lmodbat/bes/linkedlist/LinkedList$Node<TE;>;
    // declaration: newNode extends modbat.bes.linkedlist.LinkedList$Node<E>
    MAXSTACK = 5
    MAXLOCALS = 4

  // access flags 0x0
  // signature (TE;Lmodbat/bes/linkedlist/LinkedList$Node<TE;>;)V
  // declaration: void linkBefore(E, modbat.bes.linkedlist.LinkedList$Node<E>)
  linkBefore(Ljava/lang/Object;Lmodbat/bes/linkedlist/LinkedList$Node;)V
   L0
    LINENUMBER 166 L0
    ALOAD 2
    GETFIELD modbat/bes/linkedlist/LinkedList$Node.prev : Lmodbat/bes/linkedlist/LinkedList$Node;
    ASTORE 3
   L1
    LINENUMBER 167 L1
    NEW modbat/bes/linkedlist/LinkedList$Node
    DUP
    ALOAD 3
    ALOAD 1
    ALOAD 2
    INVOKESPECIAL modbat/bes/linkedlist/LinkedList$Node.<init> (Lmodbat/bes/linkedlist/LinkedList$Node;Ljava/lang/Object;Lmodbat/bes/linkedlist/LinkedList$Node;)V
    ASTORE 4
   L2
    LINENUMBER 168 L2
    ALOAD 2
    ALOAD 4
    PUTFIELD modbat/bes/linkedlist/LinkedList$Node.prev : Lmodbat/bes/linkedlist/LinkedList$Node;
   L3
    LINENUMBER 169 L3
    ALOAD 3
    IFNONNULL L4
   L5
    LINENUMBER 170 L5
    ALOAD 0
    ALOAD 4
    PUTFIELD modbat/bes/linkedlist/LinkedList.first : Lmodbat/bes/linkedlist/LinkedList$Node;
    GOTO L6
   L4
    LINENUMBER 172 L4
   FRAME FULL [modbat/bes/linkedlist/LinkedList java/lang/Object modbat/bes/linkedlist/LinkedList$Node modbat/bes/linkedlist/LinkedList$Node modbat/bes/linkedlist/LinkedList$Node] []
    ALOAD 3
    ALOAD 4
    PUTFIELD modbat/bes/linkedlist/LinkedList$Node.next : Lmodbat/bes/linkedlist/LinkedList$Node;
   L6
    LINENUMBER 173 L6
   FRAME FULL [modbat/bes/linkedlist/LinkedList java/lang/Object modbat/bes/linkedlist/LinkedList$Node modbat/bes/linkedlist/LinkedList$Node modbat/bes/linkedlist/LinkedList$Node] []
    ALOAD 0
    DUP
    GETFIELD modbat/bes/linkedlist/LinkedList.size : I
    ICONST_1
    IADD
    PUTFIELD modbat/bes/linkedlist/LinkedList.size : I
   L7
    LINENUMBER 174 L7
    ALOAD 0
    DUP
    GETFIELD modbat/bes/linkedlist/LinkedList.modCount : I
    ICONST_1
    ISUB
    PUTFIELD modbat/bes/linkedlist/LinkedList.modCount : I
   L8
    LINENUMBER 175 L8
    RETURN
   L9
    LOCALVARIABLE this Lmodbat/bes/linkedlist/LinkedList; L0 L9 0
    // signature Lmodbat/bes/linkedlist/LinkedList<TE;>;
    // declaration: this extends modbat.bes.linkedlist.LinkedList<E>
    LOCALVARIABLE e Ljava/lang/Object; L0 L9 1
    // signature TE;
    // declaration: e extends E
    LOCALVARIABLE succ Lmodbat/bes/linkedlist/LinkedList$Node; L0 L9 2
    // signature Lmodbat/bes/linkedlist/LinkedList$Node<TE;>;
    // declaration: succ extends modbat.bes.linkedlist.LinkedList$Node<E>
    LOCALVARIABLE pred Lmodbat/bes/linkedlist/LinkedList$Node; L1 L9 3
    // signature Lmodbat/bes/linkedlist/LinkedList$Node<TE;>;
    // declaration: pred extends modbat.bes.linkedlist.LinkedList$Node<E>
    LOCALVARIABLE newNode Lmodbat/bes/linkedlist/LinkedList$Node; L2 L9 4
    // signature Lmodbat/bes/linkedlist/LinkedList$Node<TE;>;
    // declaration: newNode extends modbat.bes.linkedlist.LinkedList$Node<E>
    MAXSTACK = 5
    MAXLOCALS = 5

  // access flags 0x2
  // signature (Lmodbat/bes/linkedlist/LinkedList$Node<TE;>;)TE;
  // declaration: E unlinkFirst(modbat.bes.linkedlist.LinkedList$Node<E>)
  private unlinkFirst(Lmodbat/bes/linkedlist/LinkedList$Node;)Ljava/lang/Object;
   L0
    LINENUMBER 182 L0
    ALOAD 1
    GETFIELD modbat/bes/linkedlist/LinkedList$Node.item : Ljava/lang/Object;
    ASTORE 2
   L1
    LINENUMBER 183 L1
    ALOAD 1
    GETFIELD modbat/bes/linkedlist/LinkedList$Node.next : Lmodbat/bes/linkedlist/LinkedList$Node;
    ASTORE 3
   L2
    LINENUMBER 184 L2
    ALOAD 1
    ACONST_NULL
    PUTFIELD modbat/bes/linkedlist/LinkedList$Node.item : Ljava/lang/Object;
   L3
    LINENUMBER 185 L3
    ALOAD 1
    ACONST_NULL
    PUTFIELD modbat/bes/linkedlist/LinkedList$Node.next : Lmodbat/bes/linkedlist/LinkedList$Node;
   L4
    LINENUMBER 186 L4
    ALOAD 0
    ALOAD 3
    PUTFIELD modbat/bes/linkedlist/LinkedList.first : Lmodbat/bes/linkedlist/LinkedList$Node;
   L5
    LINENUMBER 187 L5
    ALOAD 3
    IFNONNULL L6
   L7
    LINENUMBER 188 L7
    ALOAD 0
    ACONST_NULL
    PUTFIELD modbat/bes/linkedlist/LinkedList.last : Lmodbat/bes/linkedlist/LinkedList$Node;
    GOTO L8
   L6
    LINENUMBER 190 L6
   FRAME FULL [modbat/bes/linkedlist/LinkedList modbat/bes/linkedlist/LinkedList$Node java/lang/Object modbat/bes/linkedlist/LinkedList$Node] []
    ALOAD 3
    ACONST_NULL
    PUTFIELD modbat/bes/linkedlist/LinkedList$Node.prev : Lmodbat/bes/linkedlist/LinkedList$Node;
   L8
    LINENUMBER 191 L8
   FRAME FULL [modbat/bes/linkedlist/LinkedList modbat/bes/linkedlist/LinkedList$Node java/lang/Object modbat/bes/linkedlist/LinkedList$Node] []
    ALOAD 0
    DUP
    GETFIELD modbat/bes/linkedlist/LinkedList.size : I
    ICONST_1
    ISUB
    PUTFIELD modbat/bes/linkedlist/LinkedList.size : I
   L9
    LINENUMBER 192 L9
    ALOAD 0
    DUP
    GETFIELD modbat/bes/linkedlist/LinkedList.modCount : I
    ICONST_1
    IADD
    PUTFIELD modbat/bes/linkedlist/LinkedList.modCount : I
   L10
    LINENUMBER 193 L10
    ALOAD 2
    ARETURN
   L11
    LOCALVARIABLE this Lmodbat/bes/linkedlist/LinkedList; L0 L11 0
    // signature Lmodbat/bes/linkedlist/LinkedList<TE;>;
    // declaration: this extends modbat.bes.linkedlist.LinkedList<E>
    LOCALVARIABLE f Lmodbat/bes/linkedlist/LinkedList$Node; L0 L11 1
    // signature Lmodbat/bes/linkedlist/LinkedList$Node<TE;>;
    // declaration: f extends modbat.bes.linkedlist.LinkedList$Node<E>
    LOCALVARIABLE element Ljava/lang/Object; L1 L11 2
    // signature TE;
    // declaration: element extends E
    LOCALVARIABLE next Lmodbat/bes/linkedlist/LinkedList$Node; L2 L11 3
    // signature Lmodbat/bes/linkedlist/LinkedList$Node<TE;>;
    // declaration: next extends modbat.bes.linkedlist.LinkedList$Node<E>
    MAXSTACK = 3
    MAXLOCALS = 4

  // access flags 0x2
  // signature (Lmodbat/bes/linkedlist/LinkedList$Node<TE;>;)TE;
  // declaration: E unlinkLast(modbat.bes.linkedlist.LinkedList$Node<E>)
  private unlinkLast(Lmodbat/bes/linkedlist/LinkedList$Node;)Ljava/lang/Object;
   L0
    LINENUMBER 201 L0
    ALOAD 1
    GETFIELD modbat/bes/linkedlist/LinkedList$Node.item : Ljava/lang/Object;
    ASTORE 2
   L1
    LINENUMBER 202 L1
    ALOAD 1
    GETFIELD modbat/bes/linkedlist/LinkedList$Node.prev : Lmodbat/bes/linkedlist/LinkedList$Node;
    ASTORE 3
   L2
    LINENUMBER 203 L2
    ALOAD 1
    ACONST_NULL
    PUTFIELD modbat/bes/linkedlist/LinkedList$Node.item : Ljava/lang/Object;
   L3
    LINENUMBER 204 L3
    ALOAD 1
    ACONST_NULL
    PUTFIELD modbat/bes/linkedlist/LinkedList$Node.prev : Lmodbat/bes/linkedlist/LinkedList$Node;
   L4
    LINENUMBER 205 L4
    ALOAD 0
    ALOAD 3
    PUTFIELD modbat/bes/linkedlist/LinkedList.last : Lmodbat/bes/linkedlist/LinkedList$Node;
   L5
    LINENUMBER 206 L5
    ALOAD 3
    IFNONNULL L6
   L7
    LINENUMBER 207 L7
    ALOAD 0
    ACONST_NULL
    PUTFIELD modbat/bes/linkedlist/LinkedList.first : Lmodbat/bes/linkedlist/LinkedList$Node;
    GOTO L8
   L6
    LINENUMBER 209 L6
   FRAME FULL [modbat/bes/linkedlist/LinkedList modbat/bes/linkedlist/LinkedList$Node java/lang/Object modbat/bes/linkedlist/LinkedList$Node] []
    ALOAD 3
    ACONST_NULL
    PUTFIELD modbat/bes/linkedlist/LinkedList$Node.next : Lmodbat/bes/linkedlist/LinkedList$Node;
   L8
    LINENUMBER 210 L8
   FRAME FULL [modbat/bes/linkedlist/LinkedList modbat/bes/linkedlist/LinkedList$Node java/lang/Object modbat/bes/linkedlist/LinkedList$Node] []
    ALOAD 0
    DUP
    GETFIELD modbat/bes/linkedlist/LinkedList.size : I
    ICONST_1
    ISUB
    PUTFIELD modbat/bes/linkedlist/LinkedList.size : I
   L9
    LINENUMBER 211 L9
    ALOAD 0
    DUP
    GETFIELD modbat/bes/linkedlist/LinkedList.modCount : I
    ICONST_1
    IADD
    PUTFIELD modbat/bes/linkedlist/LinkedList.modCount : I
   L10
    LINENUMBER 212 L10
    ALOAD 2
    ARETURN
   L11
    LOCALVARIABLE this Lmodbat/bes/linkedlist/LinkedList; L0 L11 0
    // signature Lmodbat/bes/linkedlist/LinkedList<TE;>;
    // declaration: this extends modbat.bes.linkedlist.LinkedList<E>
    LOCALVARIABLE l Lmodbat/bes/linkedlist/LinkedList$Node; L0 L11 1
    // signature Lmodbat/bes/linkedlist/LinkedList$Node<TE;>;
    // declaration: l extends modbat.bes.linkedlist.LinkedList$Node<E>
    LOCALVARIABLE element Ljava/lang/Object; L1 L11 2
    // signature TE;
    // declaration: element extends E
    LOCALVARIABLE prev Lmodbat/bes/linkedlist/LinkedList$Node; L2 L11 3
    // signature Lmodbat/bes/linkedlist/LinkedList$Node<TE;>;
    // declaration: prev extends modbat.bes.linkedlist.LinkedList$Node<E>
    MAXSTACK = 3
    MAXLOCALS = 4

  // access flags 0x0
  // signature (Lmodbat/bes/linkedlist/LinkedList$Node<TE;>;)TE;
  // declaration: E unlink(modbat.bes.linkedlist.LinkedList$Node<E>)
  unlink(Lmodbat/bes/linkedlist/LinkedList$Node;)Ljava/lang/Object;
   L0
    LINENUMBER 220 L0
    ALOAD 1
    GETFIELD modbat/bes/linkedlist/LinkedList$Node.item : Ljava/lang/Object;
    ASTORE 2
   L1
    LINENUMBER 221 L1
    ALOAD 1
    GETFIELD modbat/bes/linkedlist/LinkedList$Node.next : Lmodbat/bes/linkedlist/LinkedList$Node;
    ASTORE 3
   L2
    LINENUMBER 222 L2
    ALOAD 1
    GETFIELD modbat/bes/linkedlist/LinkedList$Node.prev : Lmodbat/bes/linkedlist/LinkedList$Node;
    ASTORE 4
   L3
    LINENUMBER 224 L3
    ALOAD 4
    IFNONNULL L4
   L5
    LINENUMBER 225 L5
    ALOAD 0
    ALOAD 3
    PUTFIELD modbat/bes/linkedlist/LinkedList.first : Lmodbat/bes/linkedlist/LinkedList$Node;
    GOTO L6
   L4
    LINENUMBER 227 L4
   FRAME FULL [modbat/bes/linkedlist/LinkedList modbat/bes/linkedlist/LinkedList$Node java/lang/Object modbat/bes/linkedlist/LinkedList$Node modbat/bes/linkedlist/LinkedList$Node] []
    ALOAD 4
    ALOAD 3
    PUTFIELD modbat/bes/linkedlist/LinkedList$Node.next : Lmodbat/bes/linkedlist/LinkedList$Node;
   L7
    LINENUMBER 228 L7
    ALOAD 1
    ACONST_NULL
    PUTFIELD modbat/bes/linkedlist/LinkedList$Node.prev : Lmodbat/bes/linkedlist/LinkedList$Node;
   L6
    LINENUMBER 231 L6
   FRAME FULL [modbat/bes/linkedlist/LinkedList modbat/bes/linkedlist/LinkedList$Node java/lang/Object modbat/bes/linkedlist/LinkedList$Node modbat/bes/linkedlist/LinkedList$Node] []
    ALOAD 3
    IFNONNULL L8
   L9
    LINENUMBER 232 L9
    ALOAD 0
    ALOAD 4
    PUTFIELD modbat/bes/linkedlist/LinkedList.last : Lmodbat/bes/linkedlist/LinkedList$Node;
    GOTO L10
   L8
    LINENUMBER 234 L8
   FRAME FULL [modbat/bes/linkedlist/LinkedList modbat/bes/linkedlist/LinkedList$Node java/lang/Object modbat/bes/linkedlist/LinkedList$Node modbat/bes/linkedlist/LinkedList$Node] []
    ALOAD 3
    ALOAD 4
    PUTFIELD modbat/bes/linkedlist/LinkedList$Node.prev : Lmodbat/bes/linkedlist/LinkedList$Node;
   L11
    LINENUMBER 235 L11
    ALOAD 1
    ACONST_NULL
    PUTFIELD modbat/bes/linkedlist/LinkedList$Node.next : Lmodbat/bes/linkedlist/LinkedList$Node;
   L10
    LINENUMBER 238 L10
   FRAME FULL [modbat/bes/linkedlist/LinkedList modbat/bes/linkedlist/LinkedList$Node java/lang/Object modbat/bes/linkedlist/LinkedList$Node modbat/bes/linkedlist/LinkedList$Node] []
    ALOAD 1
    ACONST_NULL
    PUTFIELD modbat/bes/linkedlist/LinkedList$Node.item : Ljava/lang/Object;
   L12
    LINENUMBER 239 L12
    ALOAD 0
    DUP
    GETFIELD modbat/bes/linkedlist/LinkedList.size : I
    ICONST_1
    ISUB
    PUTFIELD modbat/bes/linkedlist/LinkedList.size : I
   L13
    LINENUMBER 240 L13
    ALOAD 0
    DUP
    GETFIELD modbat/bes/linkedlist/LinkedList.modCount : I
    ICONST_1
    IADD
    PUTFIELD modbat/bes/linkedlist/LinkedList.modCount : I
   L14
    LINENUMBER 241 L14
    ALOAD 2
    ARETURN
   L15
    LOCALVARIABLE this Lmodbat/bes/linkedlist/LinkedList; L0 L15 0
    // signature Lmodbat/bes/linkedlist/LinkedList<TE;>;
    // declaration: this extends modbat.bes.linkedlist.LinkedList<E>
    LOCALVARIABLE x Lmodbat/bes/linkedlist/LinkedList$Node; L0 L15 1
    // signature Lmodbat/bes/linkedlist/LinkedList$Node<TE;>;
    // declaration: x extends modbat.bes.linkedlist.LinkedList$Node<E>
    LOCALVARIABLE element Ljava/lang/Object; L1 L15 2
    // signature TE;
    // declaration: element extends E
    LOCALVARIABLE next Lmodbat/bes/linkedlist/LinkedList$Node; L2 L15 3
    // signature Lmodbat/bes/linkedlist/LinkedList$Node<TE;>;
    // declaration: next extends modbat.bes.linkedlist.LinkedList$Node<E>
    LOCALVARIABLE prev Lmodbat/bes/linkedlist/LinkedList$Node; L3 L15 4
    // signature Lmodbat/bes/linkedlist/LinkedList$Node<TE;>;
    // declaration: prev extends modbat.bes.linkedlist.LinkedList$Node<E>
    MAXSTACK = 3
    MAXLOCALS = 5

  // access flags 0x1
  // signature ()TE;
  // declaration: E getFirst()
  public getFirst()Ljava/lang/Object;
   L0
    LINENUMBER 251 L0
    ALOAD 0
    GETFIELD modbat/bes/linkedlist/LinkedList.first : Lmodbat/bes/linkedlist/LinkedList$Node;
    ASTORE 1
   L1
    LINENUMBER 252 L1
    ALOAD 1
    IFNONNULL L2
   L3
    LINENUMBER 253 L3
    NEW java/util/NoSuchElementException
    DUP
    INVOKESPECIAL java/util/NoSuchElementException.<init> ()V
    ATHROW
   L2
    LINENUMBER 254 L2
   FRAME FULL [modbat/bes/linkedlist/LinkedList modbat/bes/linkedlist/LinkedList$Node] []
    ALOAD 1
    GETFIELD modbat/bes/linkedlist/LinkedList$Node.item : Ljava/lang/Object;
    ARETURN
   L4
    LOCALVARIABLE this Lmodbat/bes/linkedlist/LinkedList; L0 L4 0
    // signature Lmodbat/bes/linkedlist/LinkedList<TE;>;
    // declaration: this extends modbat.bes.linkedlist.LinkedList<E>
    LOCALVARIABLE f Lmodbat/bes/linkedlist/LinkedList$Node; L1 L4 1
    // signature Lmodbat/bes/linkedlist/LinkedList$Node<TE;>;
    // declaration: f extends modbat.bes.linkedlist.LinkedList$Node<E>
    MAXSTACK = 2
    MAXLOCALS = 2

  // access flags 0x1
  // signature ()TE;
  // declaration: E getLast()
  public getLast()Ljava/lang/Object;
   L0
    LINENUMBER 264 L0
    ALOAD 0
    GETFIELD modbat/bes/linkedlist/LinkedList.last : Lmodbat/bes/linkedlist/LinkedList$Node;
    ASTORE 1
   L1
    LINENUMBER 265 L1
    ALOAD 1
    IFNONNULL L2
   L3
    LINENUMBER 266 L3
    NEW java/util/NoSuchElementException
    DUP
    INVOKESPECIAL java/util/NoSuchElementException.<init> ()V
    ATHROW
   L2
    LINENUMBER 267 L2
   FRAME FULL [modbat/bes/linkedlist/LinkedList modbat/bes/linkedlist/LinkedList$Node] []
    ALOAD 1
    GETFIELD modbat/bes/linkedlist/LinkedList$Node.item : Ljava/lang/Object;
    ARETURN
   L4
    LOCALVARIABLE this Lmodbat/bes/linkedlist/LinkedList; L0 L4 0
    // signature Lmodbat/bes/linkedlist/LinkedList<TE;>;
    // declaration: this extends modbat.bes.linkedlist.LinkedList<E>
    LOCALVARIABLE l Lmodbat/bes/linkedlist/LinkedList$Node; L1 L4 1
    // signature Lmodbat/bes/linkedlist/LinkedList$Node<TE;>;
    // declaration: l extends modbat.bes.linkedlist.LinkedList$Node<E>
    MAXSTACK = 2
    MAXLOCALS = 2

  // access flags 0x1
  // signature ()TE;
  // declaration: E removeFirst()
  public removeFirst()Ljava/lang/Object;
   L0
    LINENUMBER 277 L0
    ALOAD 0
    GETFIELD modbat/bes/linkedlist/LinkedList.first : Lmodbat/bes/linkedlist/LinkedList$Node;
    ASTORE 1
   L1
    LINENUMBER 278 L1
    ALOAD 1
    IFNONNULL L2
   L3
    LINENUMBER 279 L3
    NEW java/util/NoSuchElementException
    DUP
    INVOKESPECIAL java/util/NoSuchElementException.<init> ()V
    ATHROW
   L2
    LINENUMBER 280 L2
   FRAME FULL [modbat/bes/linkedlist/LinkedList modbat/bes/linkedlist/LinkedList$Node] []
    ALOAD 0
    ALOAD 1
    INVOKEVIRTUAL modbat/bes/linkedlist/LinkedList.unlinkFirst (Lmodbat/bes/linkedlist/LinkedList$Node;)Ljava/lang/Object;
    ARETURN
   L4
    LOCALVARIABLE this Lmodbat/bes/linkedlist/LinkedList; L0 L4 0
    // signature Lmodbat/bes/linkedlist/LinkedList<TE;>;
    // declaration: this extends modbat.bes.linkedlist.LinkedList<E>
    LOCALVARIABLE f Lmodbat/bes/linkedlist/LinkedList$Node; L1 L4 1
    // signature Lmodbat/bes/linkedlist/LinkedList$Node<TE;>;
    // declaration: f extends modbat.bes.linkedlist.LinkedList$Node<E>
    MAXSTACK = 2
    MAXLOCALS = 2

  // access flags 0x1
  // signature ()TE;
  // declaration: E removeLast()
  public removeLast()Ljava/lang/Object;
   L0
    LINENUMBER 290 L0
    ALOAD 0
    GETFIELD modbat/bes/linkedlist/LinkedList.last : Lmodbat/bes/linkedlist/LinkedList$Node;
    ASTORE 1
   L1
    LINENUMBER 291 L1
    ALOAD 1
    IFNONNULL L2
   L3
    LINENUMBER 292 L3
    NEW java/util/NoSuchElementException
    DUP
    INVOKESPECIAL java/util/NoSuchElementException.<init> ()V
    ATHROW
   L2
    LINENUMBER 293 L2
   FRAME FULL [modbat/bes/linkedlist/LinkedList modbat/bes/linkedlist/LinkedList$Node] []
    ALOAD 0
    ALOAD 1
    INVOKEVIRTUAL modbat/bes/linkedlist/LinkedList.unlinkLast (Lmodbat/bes/linkedlist/LinkedList$Node;)Ljava/lang/Object;
    ARETURN
   L4
    LOCALVARIABLE this Lmodbat/bes/linkedlist/LinkedList; L0 L4 0
    // signature Lmodbat/bes/linkedlist/LinkedList<TE;>;
    // declaration: this extends modbat.bes.linkedlist.LinkedList<E>
    LOCALVARIABLE l Lmodbat/bes/linkedlist/LinkedList$Node; L1 L4 1
    // signature Lmodbat/bes/linkedlist/LinkedList$Node<TE;>;
    // declaration: l extends modbat.bes.linkedlist.LinkedList$Node<E>
    MAXSTACK = 2
    MAXLOCALS = 2

  // access flags 0x1
  // signature (TE;)V
  // declaration: void addFirst(E)
  public addFirst(Ljava/lang/Object;)V
   L0
    LINENUMBER 302 L0
    ALOAD 0
    ALOAD 1
    INVOKEVIRTUAL modbat/bes/linkedlist/LinkedList.linkFirst (Ljava/lang/Object;)V
   L1
    LINENUMBER 303 L1
    RETURN
   L2
    LOCALVARIABLE this Lmodbat/bes/linkedlist/LinkedList; L0 L2 0
    // signature Lmodbat/bes/linkedlist/LinkedList<TE;>;
    // declaration: this extends modbat.bes.linkedlist.LinkedList<E>
    LOCALVARIABLE e Ljava/lang/Object; L0 L2 1
    // signature TE;
    // declaration: e extends E
    MAXSTACK = 2
    MAXLOCALS = 2

  // access flags 0x1
  // signature (TE;)V
  // declaration: void addLast(E)
  public addLast(Ljava/lang/Object;)V
   L0
    LINENUMBER 313 L0
    ALOAD 0
    ALOAD 1
    INVOKEVIRTUAL modbat/bes/linkedlist/LinkedList.linkLast (Ljava/lang/Object;)V
   L1
    LINENUMBER 314 L1
    RETURN
   L2
    LOCALVARIABLE this Lmodbat/bes/linkedlist/LinkedList; L0 L2 0
    // signature Lmodbat/bes/linkedlist/LinkedList<TE;>;
    // declaration: this extends modbat.bes.linkedlist.LinkedList<E>
    LOCALVARIABLE e Ljava/lang/Object; L0 L2 1
    // signature TE;
    // declaration: e extends E
    MAXSTACK = 2
    MAXLOCALS = 2

  // access flags 0x1
  public contains(Ljava/lang/Object;)Z
   L0
    LINENUMBER 326 L0
    ALOAD 0
    ALOAD 1
    INVOKEVIRTUAL modbat/bes/linkedlist/LinkedList.indexOf (Ljava/lang/Object;)I
    ICONST_M1
    IF_ICMPEQ L1
    ICONST_1
    GOTO L2
   L1
   FRAME FULL [modbat/bes/linkedlist/LinkedList java/lang/Object] []
    ICONST_0
   L2
   FRAME FULL [modbat/bes/linkedlist/LinkedList java/lang/Object] [I]
    IRETURN
   L3
    LOCALVARIABLE this Lmodbat/bes/linkedlist/LinkedList; L0 L3 0
    // signature Lmodbat/bes/linkedlist/LinkedList<TE;>;
    // declaration: this extends modbat.bes.linkedlist.LinkedList<E>
    LOCALVARIABLE o Ljava/lang/Object; L0 L3 1
    MAXSTACK = 2
    MAXLOCALS = 2

  // access flags 0x1
  public size()I
   L0
    LINENUMBER 335 L0
    ALOAD 0
    GETFIELD modbat/bes/linkedlist/LinkedList.size : I
    IRETURN
   L1
    LOCALVARIABLE this Lmodbat/bes/linkedlist/LinkedList; L0 L1 0
    // signature Lmodbat/bes/linkedlist/LinkedList<TE;>;
    // declaration: this extends modbat.bes.linkedlist.LinkedList<E>
    MAXSTACK = 1
    MAXLOCALS = 1

  // access flags 0x1
  // signature (TE;)Z
  // declaration: boolean add(E)
  public add(Ljava/lang/Object;)Z
   L0
    LINENUMBER 347 L0
    ALOAD 0
    ALOAD 1
    INVOKEVIRTUAL modbat/bes/linkedlist/LinkedList.linkLast (Ljava/lang/Object;)V
   L1
    LINENUMBER 348 L1
    ICONST_1
    IRETURN
   L2
    LOCALVARIABLE this Lmodbat/bes/linkedlist/LinkedList; L0 L2 0
    // signature Lmodbat/bes/linkedlist/LinkedList<TE;>;
    // declaration: this extends modbat.bes.linkedlist.LinkedList<E>
    LOCALVARIABLE e Ljava/lang/Object; L0 L2 1
    // signature TE;
    // declaration: e extends E
    MAXSTACK = 2
    MAXLOCALS = 2

  // access flags 0x1
  public remove(Ljava/lang/Object;)Z
   L0
    LINENUMBER 365 L0
    ALOAD 1
    IFNONNULL L1
   L2
    LINENUMBER 366 L2
    ALOAD 0
    GETFIELD modbat/bes/linkedlist/LinkedList.first : Lmodbat/bes/linkedlist/LinkedList$Node;
    ASTORE 2
   L3
   FRAME FULL [modbat/bes/linkedlist/LinkedList java/lang/Object modbat/bes/linkedlist/LinkedList$Node] []
    ALOAD 2
    IFNULL L4
   L5
    LINENUMBER 367 L5
    ALOAD 2
    GETFIELD modbat/bes/linkedlist/LinkedList$Node.item : Ljava/lang/Object;
    IFNONNULL L6
   L7
    LINENUMBER 368 L7
    ALOAD 0
    ALOAD 2
    INVOKEVIRTUAL modbat/bes/linkedlist/LinkedList.unlink (Lmodbat/bes/linkedlist/LinkedList$Node;)Ljava/lang/Object;
    POP
   L8
    LINENUMBER 369 L8
    ICONST_1
    IRETURN
   L6
    LINENUMBER 366 L6
   FRAME FULL [modbat/bes/linkedlist/LinkedList java/lang/Object modbat/bes/linkedlist/LinkedList$Node] []
    ALOAD 2
    GETFIELD modbat/bes/linkedlist/LinkedList$Node.next : Lmodbat/bes/linkedlist/LinkedList$Node;
    ASTORE 2
    GOTO L3
   L4
   FRAME FULL [modbat/bes/linkedlist/LinkedList java/lang/Object modbat/bes/linkedlist/LinkedList$Node] []
    GOTO L9
   L1
    LINENUMBER 373 L1
   FRAME FULL [modbat/bes/linkedlist/LinkedList java/lang/Object] []
    ALOAD 0
    GETFIELD modbat/bes/linkedlist/LinkedList.first : Lmodbat/bes/linkedlist/LinkedList$Node;
    ASTORE 2
   L10
   FRAME FULL [modbat/bes/linkedlist/LinkedList java/lang/Object modbat/bes/linkedlist/LinkedList$Node] []
    ALOAD 2
    IFNULL L9
   L11
    LINENUMBER 374 L11
    ALOAD 1
    ALOAD 2
    GETFIELD modbat/bes/linkedlist/LinkedList$Node.item : Ljava/lang/Object;
    INVOKEVIRTUAL java/lang/Object.equals (Ljava/lang/Object;)Z
    IFEQ L12
   L13
    LINENUMBER 375 L13
    ALOAD 0
    ALOAD 2
    INVOKEVIRTUAL modbat/bes/linkedlist/LinkedList.unlink (Lmodbat/bes/linkedlist/LinkedList$Node;)Ljava/lang/Object;
    POP
   L14
    LINENUMBER 376 L14
    ICONST_1
    IRETURN
   L12
    LINENUMBER 373 L12
   FRAME FULL [modbat/bes/linkedlist/LinkedList java/lang/Object modbat/bes/linkedlist/LinkedList$Node] []
    ALOAD 2
    GETFIELD modbat/bes/linkedlist/LinkedList$Node.next : Lmodbat/bes/linkedlist/LinkedList$Node;
    ASTORE 2
    GOTO L10
   L9
    LINENUMBER 380 L9
   FRAME FULL [modbat/bes/linkedlist/LinkedList java/lang/Object modbat/bes/linkedlist/LinkedList$Node] []
    ICONST_0
    IRETURN
   L15
    LOCALVARIABLE x Lmodbat/bes/linkedlist/LinkedList$Node; L3 L4 2
    // signature Lmodbat/bes/linkedlist/LinkedList$Node<TE;>;
    // declaration: x extends modbat.bes.linkedlist.LinkedList$Node<E>
    LOCALVARIABLE x Lmodbat/bes/linkedlist/LinkedList$Node; L10 L9 2
    // signature Lmodbat/bes/linkedlist/LinkedList$Node<TE;>;
    // declaration: x extends modbat.bes.linkedlist.LinkedList$Node<E>
    LOCALVARIABLE this Lmodbat/bes/linkedlist/LinkedList; L0 L15 0
    // signature Lmodbat/bes/linkedlist/LinkedList<TE;>;
    // declaration: this extends modbat.bes.linkedlist.LinkedList<E>
    LOCALVARIABLE o Ljava/lang/Object; L0 L15 1
    MAXSTACK = 2
    MAXLOCALS = 3

  // access flags 0x1
  // signature (Ljava/util/Collection<+TE;>;)Z
  // declaration: boolean addAll(java.util.Collection<? extends E>)
  public addAll(Ljava/util/Collection;)Z
   L0
    LINENUMBER 396 L0
    ALOAD 0
    ALOAD 0
    GETFIELD modbat/bes/linkedlist/LinkedList.size : I
    ALOAD 1
    INVOKEVIRTUAL modbat/bes/linkedlist/LinkedList.addAll (ILjava/util/Collection;)Z
    IRETURN
   L1
    LOCALVARIABLE this Lmodbat/bes/linkedlist/LinkedList; L0 L1 0
    // signature Lmodbat/bes/linkedlist/LinkedList<TE;>;
    // declaration: this extends modbat.bes.linkedlist.LinkedList<E>
    LOCALVARIABLE c Ljava/util/Collection; L0 L1 1
    // signature Ljava/util/Collection<+TE;>;
    // declaration: c extends java.util.Collection<? extends E>
    MAXSTACK = 3
    MAXLOCALS = 2

  // access flags 0x1
  // signature (ILjava/util/Collection<+TE;>;)Z
  // declaration: boolean addAll(int, java.util.Collection<? extends E>)
  public addAll(ILjava/util/Collection;)Z
   L0
    LINENUMBER 415 L0
    ALOAD 0
    ILOAD 1
    INVOKEVIRTUAL modbat/bes/linkedlist/LinkedList.checkPositionIndex (I)V
   L1
    LINENUMBER 417 L1
    ALOAD 2
    INVOKEINTERFACE java/util/Collection.toArray ()[Ljava/lang/Object; (itf)
    ASTORE 3
   L2
    LINENUMBER 418 L2
    ALOAD 3
    ARRAYLENGTH
    ISTORE 4
   L3
    LINENUMBER 419 L3
    ILOAD 4
    IFNE L4
   L5
    LINENUMBER 420 L5
    ICONST_0
    IRETURN
   L4
    LINENUMBER 423 L4
   FRAME FULL [modbat/bes/linkedlist/LinkedList I java/util/Collection [Ljava/lang/Object; I] []
    ILOAD 1
    ALOAD 0
    GETFIELD modbat/bes/linkedlist/LinkedList.size : I
    IF_ICMPNE L6
   L7
    LINENUMBER 424 L7
    ACONST_NULL
    ASTORE 6
   L8
    LINENUMBER 425 L8
    ALOAD 0
    GETFIELD modbat/bes/linkedlist/LinkedList.last : Lmodbat/bes/linkedlist/LinkedList$Node;
    ASTORE 5
   L9
    GOTO L10
   L6
    LINENUMBER 427 L6
   FRAME FULL [modbat/bes/linkedlist/LinkedList I java/util/Collection [Ljava/lang/Object; I] []
    ALOAD 0
    ILOAD 1
    INVOKEVIRTUAL modbat/bes/linkedlist/LinkedList.node (I)Lmodbat/bes/linkedlist/LinkedList$Node;
    ASTORE 6
   L11
    LINENUMBER 428 L11
    ALOAD 6
    GETFIELD modbat/bes/linkedlist/LinkedList$Node.prev : Lmodbat/bes/linkedlist/LinkedList$Node;
    ASTORE 5
   L10
    LINENUMBER 431 L10
   FRAME FULL [modbat/bes/linkedlist/LinkedList I java/util/Collection [Ljava/lang/Object; I modbat/bes/linkedlist/LinkedList$Node modbat/bes/linkedlist/LinkedList$Node] []
    ALOAD 3
    ASTORE 7
    ALOAD 7
    ARRAYLENGTH
    ISTORE 8
    ICONST_0
    ISTORE 9
   L12
   FRAME FULL [modbat/bes/linkedlist/LinkedList I java/util/Collection [Ljava/lang/Object; I modbat/bes/linkedlist/LinkedList$Node modbat/bes/linkedlist/LinkedList$Node [Ljava/lang/Object; I I] []
    ILOAD 9
    ILOAD 8
    IF_ICMPGE L13
    ALOAD 7
    ILOAD 9
    AALOAD
    ASTORE 10
   L14
    LINENUMBER 432 L14
    ALOAD 10
    ASTORE 11
   L15
    LINENUMBER 433 L15
    NEW modbat/bes/linkedlist/LinkedList$Node
    DUP
    ALOAD 5
    ALOAD 11
    ACONST_NULL
    INVOKESPECIAL modbat/bes/linkedlist/LinkedList$Node.<init> (Lmodbat/bes/linkedlist/LinkedList$Node;Ljava/lang/Object;Lmodbat/bes/linkedlist/LinkedList$Node;)V
    ASTORE 12
   L16
    LINENUMBER 434 L16
    ALOAD 5
    IFNONNULL L17
   L18
    LINENUMBER 435 L18
    ALOAD 0
    ALOAD 12
    PUTFIELD modbat/bes/linkedlist/LinkedList.first : Lmodbat/bes/linkedlist/LinkedList$Node;
    GOTO L19
   L17
    LINENUMBER 437 L17
   FRAME FULL [modbat/bes/linkedlist/LinkedList I java/util/Collection [Ljava/lang/Object; I modbat/bes/linkedlist/LinkedList$Node modbat/bes/linkedlist/LinkedList$Node [Ljava/lang/Object; I I java/lang/Object java/lang/Object modbat/bes/linkedlist/LinkedList$Node] []
    ALOAD 5
    ALOAD 12
    PUTFIELD modbat/bes/linkedlist/LinkedList$Node.next : Lmodbat/bes/linkedlist/LinkedList$Node;
   L19
    LINENUMBER 438 L19
   FRAME FULL [modbat/bes/linkedlist/LinkedList I java/util/Collection [Ljava/lang/Object; I modbat/bes/linkedlist/LinkedList$Node modbat/bes/linkedlist/LinkedList$Node [Ljava/lang/Object; I I java/lang/Object java/lang/Object modbat/bes/linkedlist/LinkedList$Node] []
    ALOAD 12
    ASTORE 5
   L20
    LINENUMBER 431 L20
    IINC 9 1
    GOTO L12
   L13
    LINENUMBER 441 L13
   FRAME FULL [modbat/bes/linkedlist/LinkedList I java/util/Collection [Ljava/lang/Object; I modbat/bes/linkedlist/LinkedList$Node modbat/bes/linkedlist/LinkedList$Node [Ljava/lang/Object; I I] []
    ALOAD 6
    IFNONNULL L21
   L22
    LINENUMBER 442 L22
    ALOAD 0
    ALOAD 5
    PUTFIELD modbat/bes/linkedlist/LinkedList.last : Lmodbat/bes/linkedlist/LinkedList$Node;
    GOTO L23
   L21
    LINENUMBER 444 L21
   FRAME FULL [modbat/bes/linkedlist/LinkedList I java/util/Collection [Ljava/lang/Object; I modbat/bes/linkedlist/LinkedList$Node modbat/bes/linkedlist/LinkedList$Node [Ljava/lang/Object; I I] []
    ALOAD 5
    ALOAD 6
    PUTFIELD modbat/bes/linkedlist/LinkedList$Node.next : Lmodbat/bes/linkedlist/LinkedList$Node;
   L24
    LINENUMBER 445 L24
    ALOAD 6
    ALOAD 5
    PUTFIELD modbat/bes/linkedlist/LinkedList$Node.prev : Lmodbat/bes/linkedlist/LinkedList$Node;
   L23
    LINENUMBER 448 L23
   FRAME FULL [modbat/bes/linkedlist/LinkedList I java/util/Collection [Ljava/lang/Object; I modbat/bes/linkedlist/LinkedList$Node modbat/bes/linkedlist/LinkedList$Node [Ljava/lang/Object; I I] []
    ALOAD 0
    DUP
    GETFIELD modbat/bes/linkedlist/LinkedList.size : I
    ILOAD 4
    IADD
    PUTFIELD modbat/bes/linkedlist/LinkedList.size : I
   L25
    LINENUMBER 449 L25
    ALOAD 0
    DUP
    GETFIELD modbat/bes/linkedlist/LinkedList.modCount : I
    ICONST_1
    IADD
    PUTFIELD modbat/bes/linkedlist/LinkedList.modCount : I
   L26
    LINENUMBER 450 L26
    ICONST_1
    IRETURN
   L27
    LOCALVARIABLE pred Lmodbat/bes/linkedlist/LinkedList$Node; L9 L6 5
    // signature Lmodbat/bes/linkedlist/LinkedList$Node<TE;>;
    // declaration: pred extends modbat.bes.linkedlist.LinkedList$Node<E>
    LOCALVARIABLE succ Lmodbat/bes/linkedlist/LinkedList$Node; L8 L6 6
    // signature Lmodbat/bes/linkedlist/LinkedList$Node<TE;>;
    // declaration: succ extends modbat.bes.linkedlist.LinkedList$Node<E>
    LOCALVARIABLE e Ljava/lang/Object; L15 L20 11
    // signature TE;
    // declaration: e extends E
    LOCALVARIABLE newNode Lmodbat/bes/linkedlist/LinkedList$Node; L16 L20 12
    // signature Lmodbat/bes/linkedlist/LinkedList$Node<TE;>;
    // declaration: newNode extends modbat.bes.linkedlist.LinkedList$Node<E>
    LOCALVARIABLE o Ljava/lang/Object; L14 L20 10
    LOCALVARIABLE this Lmodbat/bes/linkedlist/LinkedList; L0 L27 0
    // signature Lmodbat/bes/linkedlist/LinkedList<TE;>;
    // declaration: this extends modbat.bes.linkedlist.LinkedList<E>
    LOCALVARIABLE index I L0 L27 1
    LOCALVARIABLE c Ljava/util/Collection; L0 L27 2
    // signature Ljava/util/Collection<+TE;>;
    // declaration: c extends java.util.Collection<? extends E>
    LOCALVARIABLE a [Ljava/lang/Object; L2 L27 3
    LOCALVARIABLE numNew I L3 L27 4
    LOCALVARIABLE pred Lmodbat/bes/linkedlist/LinkedList$Node; L10 L27 5
    // signature Lmodbat/bes/linkedlist/LinkedList$Node<TE;>;
    // declaration: pred extends modbat.bes.linkedlist.LinkedList$Node<E>
    LOCALVARIABLE succ Lmodbat/bes/linkedlist/LinkedList$Node; L11 L27 6
    // signature Lmodbat/bes/linkedlist/LinkedList$Node<TE;>;
    // declaration: succ extends modbat.bes.linkedlist.LinkedList$Node<E>
    MAXSTACK = 5
    MAXLOCALS = 13

  // access flags 0x1
  public clear()V
   L0
    LINENUMBER 462 L0
    ALOAD 0
    GETFIELD modbat/bes/linkedlist/LinkedList.first : Lmodbat/bes/linkedlist/LinkedList$Node;
    ASTORE 1
   L1
   FRAME FULL [modbat/bes/linkedlist/LinkedList modbat/bes/linkedlist/LinkedList$Node] []
    ALOAD 1
    IFNULL L2
   L3
    LINENUMBER 463 L3
    ALOAD 1
    GETFIELD modbat/bes/linkedlist/LinkedList$Node.next : Lmodbat/bes/linkedlist/LinkedList$Node;
    ASTORE 2
   L4
    LINENUMBER 464 L4
    ALOAD 1
    ACONST_NULL
    PUTFIELD modbat/bes/linkedlist/LinkedList$Node.item : Ljava/lang/Object;
   L5
    LINENUMBER 465 L5
    ALOAD 1
    ACONST_NULL
    PUTFIELD modbat/bes/linkedlist/LinkedList$Node.next : Lmodbat/bes/linkedlist/LinkedList$Node;
   L6
    LINENUMBER 466 L6
    ALOAD 1
    ACONST_NULL
    PUTFIELD modbat/bes/linkedlist/LinkedList$Node.prev : Lmodbat/bes/linkedlist/LinkedList$Node;
   L7
    LINENUMBER 467 L7
    ALOAD 2
    ASTORE 1
   L8
    LINENUMBER 468 L8
    GOTO L1
   L2
    LINENUMBER 469 L2
   FRAME FULL [modbat/bes/linkedlist/LinkedList modbat/bes/linkedlist/LinkedList$Node] []
    ALOAD 0
    ALOAD 0
    ACONST_NULL
    DUP_X1
    PUTFIELD modbat/bes/linkedlist/LinkedList.last : Lmodbat/bes/linkedlist/LinkedList$Node;
    PUTFIELD modbat/bes/linkedlist/LinkedList.first : Lmodbat/bes/linkedlist/LinkedList$Node;
   L9
    LINENUMBER 470 L9
    ALOAD 0
    ICONST_0
    PUTFIELD modbat/bes/linkedlist/LinkedList.size : I
   L10
    LINENUMBER 471 L10
    ALOAD 0
    DUP
    GETFIELD modbat/bes/linkedlist/LinkedList.modCount : I
    ICONST_1
    IADD
    PUTFIELD modbat/bes/linkedlist/LinkedList.modCount : I
   L11
    LINENUMBER 472 L11
    RETURN
   L12
    LOCALVARIABLE next Lmodbat/bes/linkedlist/LinkedList$Node; L4 L8 2
    // signature Lmodbat/bes/linkedlist/LinkedList$Node<TE;>;
    // declaration: next extends modbat.bes.linkedlist.LinkedList$Node<E>
    LOCALVARIABLE x Lmodbat/bes/linkedlist/LinkedList$Node; L1 L2 1
    // signature Lmodbat/bes/linkedlist/LinkedList$Node<TE;>;
    // declaration: x extends modbat.bes.linkedlist.LinkedList$Node<E>
    LOCALVARIABLE this Lmodbat/bes/linkedlist/LinkedList; L0 L12 0
    // signature Lmodbat/bes/linkedlist/LinkedList<TE;>;
    // declaration: this extends modbat.bes.linkedlist.LinkedList<E>
    MAXSTACK = 4
    MAXLOCALS = 3

  // access flags 0x1
  // signature (I)TE;
  // declaration: E get(int)
  public get(I)Ljava/lang/Object;
   L0
    LINENUMBER 485 L0
    ALOAD 0
    ILOAD 1
    INVOKEVIRTUAL modbat/bes/linkedlist/LinkedList.checkElementIndex (I)V
   L1
    LINENUMBER 486 L1
    ALOAD 0
    ILOAD 1
    INVOKEVIRTUAL modbat/bes/linkedlist/LinkedList.node (I)Lmodbat/bes/linkedlist/LinkedList$Node;
    GETFIELD modbat/bes/linkedlist/LinkedList$Node.item : Ljava/lang/Object;
    ARETURN
   L2
    LOCALVARIABLE this Lmodbat/bes/linkedlist/LinkedList; L0 L2 0
    // signature Lmodbat/bes/linkedlist/LinkedList<TE;>;
    // declaration: this extends modbat.bes.linkedlist.LinkedList<E>
    LOCALVARIABLE index I L0 L2 1
    MAXSTACK = 2
    MAXLOCALS = 2

  // access flags 0x1
  // signature (ITE;)TE;
  // declaration: E set(int, E)
  public set(ILjava/lang/Object;)Ljava/lang/Object;
   L0
    LINENUMBER 499 L0
    ALOAD 0
    ILOAD 1
    INVOKEVIRTUAL modbat/bes/linkedlist/LinkedList.checkElementIndex (I)V
   L1
    LINENUMBER 500 L1
    ALOAD 0
    ILOAD 1
    INVOKEVIRTUAL modbat/bes/linkedlist/LinkedList.node (I)Lmodbat/bes/linkedlist/LinkedList$Node;
    ASTORE 3
   L2
    LINENUMBER 501 L2
    ALOAD 3
    GETFIELD modbat/bes/linkedlist/LinkedList$Node.item : Ljava/lang/Object;
    ASTORE 4
   L3
    LINENUMBER 502 L3
    ALOAD 3
    ALOAD 2
    PUTFIELD modbat/bes/linkedlist/LinkedList$Node.item : Ljava/lang/Object;
   L4
    LINENUMBER 503 L4
    ALOAD 4
    ARETURN
   L5
    LOCALVARIABLE this Lmodbat/bes/linkedlist/LinkedList; L0 L5 0
    // signature Lmodbat/bes/linkedlist/LinkedList<TE;>;
    // declaration: this extends modbat.bes.linkedlist.LinkedList<E>
    LOCALVARIABLE index I L0 L5 1
    LOCALVARIABLE element Ljava/lang/Object; L0 L5 2
    // signature TE;
    // declaration: element extends E
    LOCALVARIABLE x Lmodbat/bes/linkedlist/LinkedList$Node; L2 L5 3
    // signature Lmodbat/bes/linkedlist/LinkedList$Node<TE;>;
    // declaration: x extends modbat.bes.linkedlist.LinkedList$Node<E>
    LOCALVARIABLE oldVal Ljava/lang/Object; L3 L5 4
    // signature TE;
    // declaration: oldVal extends E
    MAXSTACK = 2
    MAXLOCALS = 5

  // access flags 0x1
  // signature (ITE;)V
  // declaration: void add(int, E)
  public add(ILjava/lang/Object;)V
   L0
    LINENUMBER 516 L0
    ALOAD 0
    ILOAD 1
    INVOKEVIRTUAL modbat/bes/linkedlist/LinkedList.checkPositionIndex (I)V
   L1
    LINENUMBER 518 L1
    ILOAD 1
    ALOAD 0
    GETFIELD modbat/bes/linkedlist/LinkedList.size : I
    IF_ICMPNE L2
   L3
    LINENUMBER 519 L3
    ALOAD 0
    ALOAD 2
    INVOKEVIRTUAL modbat/bes/linkedlist/LinkedList.linkLast (Ljava/lang/Object;)V
    GOTO L4
   L2
    LINENUMBER 521 L2
   FRAME FULL [modbat/bes/linkedlist/LinkedList I java/lang/Object] []
    ALOAD 0
    ALOAD 2
    ALOAD 0
    ILOAD 1
    INVOKEVIRTUAL modbat/bes/linkedlist/LinkedList.node (I)Lmodbat/bes/linkedlist/LinkedList$Node;
    INVOKEVIRTUAL modbat/bes/linkedlist/LinkedList.linkBefore (Ljava/lang/Object;Lmodbat/bes/linkedlist/LinkedList$Node;)V
   L4
    LINENUMBER 522 L4
   FRAME FULL [modbat/bes/linkedlist/LinkedList I java/lang/Object] []
    RETURN
   L5
    LOCALVARIABLE this Lmodbat/bes/linkedlist/LinkedList; L0 L5 0
    // signature Lmodbat/bes/linkedlist/LinkedList<TE;>;
    // declaration: this extends modbat.bes.linkedlist.LinkedList<E>
    LOCALVARIABLE index I L0 L5 1
    LOCALVARIABLE element Ljava/lang/Object; L0 L5 2
    // signature TE;
    // declaration: element extends E
    MAXSTACK = 4
    MAXLOCALS = 3

  // access flags 0x1
  // signature (I)TE;
  // declaration: E remove(int)
  public remove(I)Ljava/lang/Object;
   L0
    LINENUMBER 534 L0
    ALOAD 0
    ILOAD 1
    INVOKEVIRTUAL modbat/bes/linkedlist/LinkedList.checkElementIndex (I)V
   L1
    LINENUMBER 535 L1
    ALOAD 0
    ALOAD 0
    ILOAD 1
    INVOKEVIRTUAL modbat/bes/linkedlist/LinkedList.node (I)Lmodbat/bes/linkedlist/LinkedList$Node;
    INVOKEVIRTUAL modbat/bes/linkedlist/LinkedList.unlink (Lmodbat/bes/linkedlist/LinkedList$Node;)Ljava/lang/Object;
    ARETURN
   L2
    LOCALVARIABLE this Lmodbat/bes/linkedlist/LinkedList; L0 L2 0
    // signature Lmodbat/bes/linkedlist/LinkedList<TE;>;
    // declaration: this extends modbat.bes.linkedlist.LinkedList<E>
    LOCALVARIABLE index I L0 L2 1
    MAXSTACK = 3
    MAXLOCALS = 2

  // access flags 0x2
  private isElementIndex(I)Z
   L0
    LINENUMBER 542 L0
    ILOAD 1
    IFLT L1
    ILOAD 1
    ALOAD 0
    GETFIELD modbat/bes/linkedlist/LinkedList.size : I
    IF_ICMPGE L1
    ICONST_1
    GOTO L2
   L1
   FRAME FULL [modbat/bes/linkedlist/LinkedList I] []
    ICONST_0
   L2
   FRAME FULL [modbat/bes/linkedlist/LinkedList I] [I]
    IRETURN
   L3
    LOCALVARIABLE this Lmodbat/bes/linkedlist/LinkedList; L0 L3 0
    // signature Lmodbat/bes/linkedlist/LinkedList<TE;>;
    // declaration: this extends modbat.bes.linkedlist.LinkedList<E>
    LOCALVARIABLE index I L0 L3 1
    MAXSTACK = 2
    MAXLOCALS = 2

  // access flags 0x2
  private isPositionIndex(I)Z
   L0
    LINENUMBER 550 L0
    ILOAD 1
    IFLT L1
    ILOAD 1
    ALOAD 0
    GETFIELD modbat/bes/linkedlist/LinkedList.size : I
    IF_ICMPGT L1
    ICONST_1
    GOTO L2
   L1
   FRAME FULL [modbat/bes/linkedlist/LinkedList I] []
    ICONST_0
   L2
   FRAME FULL [modbat/bes/linkedlist/LinkedList I] [I]
    IRETURN
   L3
    LOCALVARIABLE this Lmodbat/bes/linkedlist/LinkedList; L0 L3 0
    // signature Lmodbat/bes/linkedlist/LinkedList<TE;>;
    // declaration: this extends modbat.bes.linkedlist.LinkedList<E>
    LOCALVARIABLE index I L0 L3 1
    MAXSTACK = 2
    MAXLOCALS = 2

  // access flags 0x2
  private outOfBoundsMsg(I)Ljava/lang/String;
   L0
    LINENUMBER 559 L0
    ILOAD 1
    ALOAD 0
    GETFIELD modbat/bes/linkedlist/LinkedList.size : I
    INVOKEDYNAMIC makeConcatWithConstants(II)Ljava/lang/String; [
      // handle kind 0x6 : INVOKESTATIC
      java/lang/invoke/StringConcatFactory.makeConcatWithConstants(Ljava/lang/invoke/MethodHandles$Lookup;Ljava/lang/String;Ljava/lang/invoke/MethodType;Ljava/lang/String;[Ljava/lang/Object;)Ljava/lang/invoke/CallSite;
      // arguments:
      "Index: \u0001, Size: \u0001"
    ]
    ARETURN
   L1
    LOCALVARIABLE this Lmodbat/bes/linkedlist/LinkedList; L0 L1 0
    // signature Lmodbat/bes/linkedlist/LinkedList<TE;>;
    // declaration: this extends modbat.bes.linkedlist.LinkedList<E>
    LOCALVARIABLE index I L0 L1 1
    MAXSTACK = 2
    MAXLOCALS = 2

  // access flags 0x2
  private checkElementIndex(I)V
   L0
    LINENUMBER 563 L0
    ALOAD 0
    ILOAD 1
    INVOKEVIRTUAL modbat/bes/linkedlist/LinkedList.isElementIndex (I)Z
    IFNE L1
   L2
    LINENUMBER 564 L2
    NEW java/lang/IndexOutOfBoundsException
    DUP
    ALOAD 0
    ILOAD 1
    INVOKEVIRTUAL modbat/bes/linkedlist/LinkedList.outOfBoundsMsg (I)Ljava/lang/String;
    INVOKESPECIAL java/lang/IndexOutOfBoundsException.<init> (Ljava/lang/String;)V
    ATHROW
   L1
    LINENUMBER 565 L1
   FRAME FULL [modbat/bes/linkedlist/LinkedList I] []
    RETURN
   L3
    LOCALVARIABLE this Lmodbat/bes/linkedlist/LinkedList; L0 L3 0
    // signature Lmodbat/bes/linkedlist/LinkedList<TE;>;
    // declaration: this extends modbat.bes.linkedlist.LinkedList<E>
    LOCALVARIABLE index I L0 L3 1
    MAXSTACK = 4
    MAXLOCALS = 2

  // access flags 0x2
  private checkPositionIndex(I)V
   L0
    LINENUMBER 568 L0
    ALOAD 0
    ILOAD 1
    INVOKEVIRTUAL modbat/bes/linkedlist/LinkedList.isPositionIndex (I)Z
    IFNE L1
   L2
    LINENUMBER 569 L2
    NEW java/lang/IndexOutOfBoundsException
    DUP
    ALOAD 0
    ILOAD 1
    INVOKEVIRTUAL modbat/bes/linkedlist/LinkedList.outOfBoundsMsg (I)Ljava/lang/String;
    INVOKESPECIAL java/lang/IndexOutOfBoundsException.<init> (Ljava/lang/String;)V
    ATHROW
   L1
    LINENUMBER 570 L1
   FRAME FULL [modbat/bes/linkedlist/LinkedList I] []
    RETURN
   L3
    LOCALVARIABLE this Lmodbat/bes/linkedlist/LinkedList; L0 L3 0
    // signature Lmodbat/bes/linkedlist/LinkedList<TE;>;
    // declaration: this extends modbat.bes.linkedlist.LinkedList<E>
    LOCALVARIABLE index I L0 L3 1
    MAXSTACK = 4
    MAXLOCALS = 2

  // access flags 0x0
  // signature (I)Lmodbat/bes/linkedlist/LinkedList$Node<TE;>;
  // declaration: modbat.bes.linkedlist.LinkedList$Node<E> node(int)
  node(I)Lmodbat/bes/linkedlist/LinkedList$Node;
   L0
    LINENUMBER 578 L0
    ILOAD 1
    ALOAD 0
    GETFIELD modbat/bes/linkedlist/LinkedList.size : I
    ICONST_1
    ISHR
    IF_ICMPGE L1
   L2
    LINENUMBER 579 L2
    ALOAD 0
    GETFIELD modbat/bes/linkedlist/LinkedList.first : Lmodbat/bes/linkedlist/LinkedList$Node;
    ASTORE 2
   L3
    LINENUMBER 580 L3
    ICONST_0
    ISTORE 3
   L4
   FRAME FULL [modbat/bes/linkedlist/LinkedList I modbat/bes/linkedlist/LinkedList$Node I] []
    ILOAD 3
    ILOAD 1
    IF_ICMPGE L5
   L6
    LINENUMBER 581 L6
    ALOAD 2
    GETFIELD modbat/bes/linkedlist/LinkedList$Node.next : Lmodbat/bes/linkedlist/LinkedList$Node;
    ASTORE 2
   L7
    LINENUMBER 580 L7
    IINC 3 1
    GOTO L4
   L5
    LINENUMBER 582 L5
   FRAME FULL [modbat/bes/linkedlist/LinkedList I modbat/bes/linkedlist/LinkedList$Node I] []
    ALOAD 2
    ARETURN
   L1
    LINENUMBER 584 L1
   FRAME FULL [modbat/bes/linkedlist/LinkedList I] []
    ALOAD 0
    GETFIELD modbat/bes/linkedlist/LinkedList.last : Lmodbat/bes/linkedlist/LinkedList$Node;
    ASTORE 2
   L8
    LINENUMBER 585 L8
    ALOAD 0
    GETFIELD modbat/bes/linkedlist/LinkedList.size : I
    ICONST_1
    ISUB
    ISTORE 3
   L9
   FRAME FULL [modbat/bes/linkedlist/LinkedList I modbat/bes/linkedlist/LinkedList$Node I] []
    ILOAD 3
    ILOAD 1
    IF_ICMPLE L10
   L11
    LINENUMBER 586 L11
    ALOAD 2
    GETFIELD modbat/bes/linkedlist/LinkedList$Node.prev : Lmodbat/bes/linkedlist/LinkedList$Node;
    ASTORE 2
   L12
    LINENUMBER 585 L12
    IINC 3 -1
    GOTO L9
   L10
    LINENUMBER 587 L10
   FRAME FULL [modbat/bes/linkedlist/LinkedList I modbat/bes/linkedlist/LinkedList$Node I] []
    ALOAD 2
    ARETURN
   L13
    LOCALVARIABLE i I L4 L5 3
    LOCALVARIABLE x Lmodbat/bes/linkedlist/LinkedList$Node; L3 L1 2
    // signature Lmodbat/bes/linkedlist/LinkedList$Node<TE;>;
    // declaration: x extends modbat.bes.linkedlist.LinkedList$Node<E>
    LOCALVARIABLE i I L9 L10 3
    LOCALVARIABLE x Lmodbat/bes/linkedlist/LinkedList$Node; L8 L13 2
    // signature Lmodbat/bes/linkedlist/LinkedList$Node<TE;>;
    // declaration: x extends modbat.bes.linkedlist.LinkedList$Node<E>
    LOCALVARIABLE this Lmodbat/bes/linkedlist/LinkedList; L0 L13 0
    // signature Lmodbat/bes/linkedlist/LinkedList<TE;>;
    // declaration: this extends modbat.bes.linkedlist.LinkedList<E>
    LOCALVARIABLE index I L0 L13 1
    MAXSTACK = 3
    MAXLOCALS = 4

  // access flags 0x1
  public indexOf(Ljava/lang/Object;)I
   L0
    LINENUMBER 605 L0
    ICONST_0
    ISTORE 2
   L1
    LINENUMBER 606 L1
    ALOAD 1
    IFNONNULL L2
   L3
    LINENUMBER 607 L3
    ALOAD 0
    GETFIELD modbat/bes/linkedlist/LinkedList.first : Lmodbat/bes/linkedlist/LinkedList$Node;
    ASTORE 3
   L4
   FRAME FULL [modbat/bes/linkedlist/LinkedList java/lang/Object I modbat/bes/linkedlist/LinkedList$Node] []
    ALOAD 3
    IFNULL L5
   L6
    LINENUMBER 608 L6
    ALOAD 3
    GETFIELD modbat/bes/linkedlist/LinkedList$Node.item : Ljava/lang/Object;
    IFNONNULL L7
   L8
    LINENUMBER 609 L8
    ILOAD 2
    IRETURN
   L7
    LINENUMBER 610 L7
   FRAME FULL [modbat/bes/linkedlist/LinkedList java/lang/Object I modbat/bes/linkedlist/LinkedList$Node] []
    IINC 2 1
   L9
    LINENUMBER 607 L9
    ALOAD 3
    GETFIELD modbat/bes/linkedlist/LinkedList$Node.next : Lmodbat/bes/linkedlist/LinkedList$Node;
    ASTORE 3
    GOTO L4
   L5
   FRAME FULL [modbat/bes/linkedlist/LinkedList java/lang/Object I modbat/bes/linkedlist/LinkedList$Node] []
    GOTO L10
   L2
    LINENUMBER 613 L2
   FRAME FULL [modbat/bes/linkedlist/LinkedList java/lang/Object I] []
    ALOAD 0
    GETFIELD modbat/bes/linkedlist/LinkedList.first : Lmodbat/bes/linkedlist/LinkedList$Node;
    ASTORE 3
   L11
   FRAME FULL [modbat/bes/linkedlist/LinkedList java/lang/Object I modbat/bes/linkedlist/LinkedList$Node] []
    ALOAD 3
    IFNULL L10
   L12
    LINENUMBER 614 L12
    ALOAD 1
    ALOAD 3
    GETFIELD modbat/bes/linkedlist/LinkedList$Node.item : Ljava/lang/Object;
    INVOKEVIRTUAL java/lang/Object.equals (Ljava/lang/Object;)Z
    IFEQ L13
   L14
    LINENUMBER 615 L14
    ILOAD 2
    IRETURN
   L13
    LINENUMBER 616 L13
   FRAME FULL [modbat/bes/linkedlist/LinkedList java/lang/Object I modbat/bes/linkedlist/LinkedList$Node] []
    IINC 2 1
   L15
    LINENUMBER 613 L15
    ALOAD 3
    GETFIELD modbat/bes/linkedlist/LinkedList$Node.next : Lmodbat/bes/linkedlist/LinkedList$Node;
    ASTORE 3
    GOTO L11
   L10
    LINENUMBER 619 L10
   FRAME FULL [modbat/bes/linkedlist/LinkedList java/lang/Object I modbat/bes/linkedlist/LinkedList$Node] []
    ICONST_M1
    IRETURN
   L16
    LOCALVARIABLE x Lmodbat/bes/linkedlist/LinkedList$Node; L4 L5 3
    // signature Lmodbat/bes/linkedlist/LinkedList$Node<TE;>;
    // declaration: x extends modbat.bes.linkedlist.LinkedList$Node<E>
    LOCALVARIABLE x Lmodbat/bes/linkedlist/LinkedList$Node; L11 L10 3
    // signature Lmodbat/bes/linkedlist/LinkedList$Node<TE;>;
    // declaration: x extends modbat.bes.linkedlist.LinkedList$Node<E>
    LOCALVARIABLE this Lmodbat/bes/linkedlist/LinkedList; L0 L16 0
    // signature Lmodbat/bes/linkedlist/LinkedList<TE;>;
    // declaration: this extends modbat.bes.linkedlist.LinkedList<E>
    LOCALVARIABLE o Ljava/lang/Object; L0 L16 1
    LOCALVARIABLE index I L1 L16 2
    MAXSTACK = 2
    MAXLOCALS = 4

  // access flags 0x1
  public lastIndexOf(Ljava/lang/Object;)I
   L0
    LINENUMBER 634 L0
    ALOAD 0
    GETFIELD modbat/bes/linkedlist/LinkedList.size : I
    ISTORE 2
   L1
    LINENUMBER 635 L1
    ALOAD 1
    IFNONNULL L2
   L3
    LINENUMBER 636 L3
    ALOAD 0
    GETFIELD modbat/bes/linkedlist/LinkedList.last : Lmodbat/bes/linkedlist/LinkedList$Node;
    ASTORE 3
   L4
   FRAME FULL [modbat/bes/linkedlist/LinkedList java/lang/Object I modbat/bes/linkedlist/LinkedList$Node] []
    ALOAD 3
    IFNULL L5
   L6
    LINENUMBER 637 L6
    IINC 2 -1
   L7
    LINENUMBER 638 L7
    ALOAD 3
    GETFIELD modbat/bes/linkedlist/LinkedList$Node.item : Ljava/lang/Object;
    IFNONNULL L8
   L9
    LINENUMBER 639 L9
    ILOAD 2
    IRETURN
   L8
    LINENUMBER 636 L8
   FRAME FULL [modbat/bes/linkedlist/LinkedList java/lang/Object I modbat/bes/linkedlist/LinkedList$Node] []
    ALOAD 3
    GETFIELD modbat/bes/linkedlist/LinkedList$Node.prev : Lmodbat/bes/linkedlist/LinkedList$Node;
    ASTORE 3
    GOTO L4
   L5
   FRAME FULL [modbat/bes/linkedlist/LinkedList java/lang/Object I modbat/bes/linkedlist/LinkedList$Node] []
    GOTO L10
   L2
    LINENUMBER 642 L2
   FRAME FULL [modbat/bes/linkedlist/LinkedList java/lang/Object I] []
    ALOAD 0
    GETFIELD modbat/bes/linkedlist/LinkedList.last : Lmodbat/bes/linkedlist/LinkedList$Node;
    ASTORE 3
   L11
   FRAME FULL [modbat/bes/linkedlist/LinkedList java/lang/Object I modbat/bes/linkedlist/LinkedList$Node] []
    ALOAD 3
    IFNULL L10
   L12
    LINENUMBER 643 L12
    IINC 2 -1
   L13
    LINENUMBER 644 L13
    ALOAD 1
    ALOAD 3
    GETFIELD modbat/bes/linkedlist/LinkedList$Node.item : Ljava/lang/Object;
    INVOKEVIRTUAL java/lang/Object.equals (Ljava/lang/Object;)Z
    IFEQ L14
   L15
    LINENUMBER 645 L15
    ILOAD 2
    IRETURN
   L14
    LINENUMBER 642 L14
   FRAME FULL [modbat/bes/linkedlist/LinkedList java/lang/Object I modbat/bes/linkedlist/LinkedList$Node] []
    ALOAD 3
    GETFIELD modbat/bes/linkedlist/LinkedList$Node.prev : Lmodbat/bes/linkedlist/LinkedList$Node;
    ASTORE 3
    GOTO L11
   L10
    LINENUMBER 648 L10
   FRAME FULL [modbat/bes/linkedlist/LinkedList java/lang/Object I modbat/bes/linkedlist/LinkedList$Node] []
    ICONST_M1
    IRETURN
   L16
    LOCALVARIABLE x Lmodbat/bes/linkedlist/LinkedList$Node; L4 L5 3
    // signature Lmodbat/bes/linkedlist/LinkedList$Node<TE;>;
    // declaration: x extends modbat.bes.linkedlist.LinkedList$Node<E>
    LOCALVARIABLE x Lmodbat/bes/linkedlist/LinkedList$Node; L11 L10 3
    // signature Lmodbat/bes/linkedlist/LinkedList$Node<TE;>;
    // declaration: x extends modbat.bes.linkedlist.LinkedList$Node<E>
    LOCALVARIABLE this Lmodbat/bes/linkedlist/LinkedList; L0 L16 0
    // signature Lmodbat/bes/linkedlist/LinkedList<TE;>;
    // declaration: this extends modbat.bes.linkedlist.LinkedList<E>
    LOCALVARIABLE o Ljava/lang/Object; L0 L16 1
    LOCALVARIABLE index I L1 L16 2
    MAXSTACK = 2
    MAXLOCALS = 4

  // access flags 0x1
  // signature ()TE;
  // declaration: E peek()
  public peek()Ljava/lang/Object;
   L0
    LINENUMBER 660 L0
    ALOAD 0
    GETFIELD modbat/bes/linkedlist/LinkedList.first : Lmodbat/bes/linkedlist/LinkedList$Node;
    ASTORE 1
   L1
    LINENUMBER 661 L1
    ALOAD 1
    IFNONNULL L2
    ACONST_NULL
    GOTO L3
   L2
   FRAME FULL [modbat/bes/linkedlist/LinkedList modbat/bes/linkedlist/LinkedList$Node] []
    ALOAD 1
    GETFIELD modbat/bes/linkedlist/LinkedList$Node.item : Ljava/lang/Object;
   L3
   FRAME FULL [modbat/bes/linkedlist/LinkedList modbat/bes/linkedlist/LinkedList$Node] [java/lang/Object]
    ARETURN
   L4
    LOCALVARIABLE this Lmodbat/bes/linkedlist/LinkedList; L0 L4 0
    // signature Lmodbat/bes/linkedlist/LinkedList<TE;>;
    // declaration: this extends modbat.bes.linkedlist.LinkedList<E>
    LOCALVARIABLE f Lmodbat/bes/linkedlist/LinkedList$Node; L1 L4 1
    // signature Lmodbat/bes/linkedlist/LinkedList$Node<TE;>;
    // declaration: f extends modbat.bes.linkedlist.LinkedList$Node<E>
    MAXSTACK = 1
    MAXLOCALS = 2

  // access flags 0x1
  // signature ()TE;
  // declaration: E element()
  public element()Ljava/lang/Object;
   L0
    LINENUMBER 672 L0
    ALOAD 0
    INVOKEVIRTUAL modbat/bes/linkedlist/LinkedList.getFirst ()Ljava/lang/Object;
    ARETURN
   L1
    LOCALVARIABLE this Lmodbat/bes/linkedlist/LinkedList; L0 L1 0
    // signature Lmodbat/bes/linkedlist/LinkedList<TE;>;
    // declaration: this extends modbat.bes.linkedlist.LinkedList<E>
    MAXSTACK = 1
    MAXLOCALS = 1

  // access flags 0x1
  // signature ()TE;
  // declaration: E poll()
  public poll()Ljava/lang/Object;
   L0
    LINENUMBER 682 L0
    ALOAD 0
    GETFIELD modbat/bes/linkedlist/LinkedList.first : Lmodbat/bes/linkedlist/LinkedList$Node;
    ASTORE 1
   L1
    LINENUMBER 683 L1
    ALOAD 1
    IFNONNULL L2
    ACONST_NULL
    GOTO L3
   L2
   FRAME FULL [modbat/bes/linkedlist/LinkedList modbat/bes/linkedlist/LinkedList$Node] []
    ALOAD 0
    ALOAD 1
    INVOKEVIRTUAL modbat/bes/linkedlist/LinkedList.unlinkFirst (Lmodbat/bes/linkedlist/LinkedList$Node;)Ljava/lang/Object;
   L3
   FRAME FULL [modbat/bes/linkedlist/LinkedList modbat/bes/linkedlist/LinkedList$Node] [java/lang/Object]
    ARETURN
   L4
    LOCALVARIABLE this Lmodbat/bes/linkedlist/LinkedList; L0 L4 0
    // signature Lmodbat/bes/linkedlist/LinkedList<TE;>;
    // declaration: this extends modbat.bes.linkedlist.LinkedList<E>
    LOCALVARIABLE f Lmodbat/bes/linkedlist/LinkedList$Node; L1 L4 1
    // signature Lmodbat/bes/linkedlist/LinkedList$Node<TE;>;
    // declaration: f extends modbat.bes.linkedlist.LinkedList$Node<E>
    MAXSTACK = 2
    MAXLOCALS = 2

  // access flags 0x1
  // signature ()TE;
  // declaration: E remove()
  public remove()Ljava/lang/Object;
   L0
    LINENUMBER 694 L0
    ALOAD 0
    INVOKEVIRTUAL modbat/bes/linkedlist/LinkedList.removeFirst ()Ljava/lang/Object;
    ARETURN
   L1
    LOCALVARIABLE this Lmodbat/bes/linkedlist/LinkedList; L0 L1 0
    // signature Lmodbat/bes/linkedlist/LinkedList<TE;>;
    // declaration: this extends modbat.bes.linkedlist.LinkedList<E>
    MAXSTACK = 1
    MAXLOCALS = 1

  // access flags 0x1
  // signature (TE;)Z
  // declaration: boolean offer(E)
  public offer(Ljava/lang/Object;)Z
   L0
    LINENUMBER 705 L0
    ALOAD 0
    ALOAD 1
    INVOKEVIRTUAL modbat/bes/linkedlist/LinkedList.add (Ljava/lang/Object;)Z
    IRETURN
   L1
    LOCALVARIABLE this Lmodbat/bes/linkedlist/LinkedList; L0 L1 0
    // signature Lmodbat/bes/linkedlist/LinkedList<TE;>;
    // declaration: this extends modbat.bes.linkedlist.LinkedList<E>
    LOCALVARIABLE e Ljava/lang/Object; L0 L1 1
    // signature TE;
    // declaration: e extends E
    MAXSTACK = 2
    MAXLOCALS = 2

  // access flags 0x1
  // signature (TE;)Z
  // declaration: boolean offerFirst(E)
  public offerFirst(Ljava/lang/Object;)Z
   L0
    LINENUMBER 717 L0
    ALOAD 0
    ALOAD 1
    INVOKEVIRTUAL modbat/bes/linkedlist/LinkedList.addFirst (Ljava/lang/Object;)V
   L1
    LINENUMBER 718 L1
    ICONST_1
    IRETURN
   L2
    LOCALVARIABLE this Lmodbat/bes/linkedlist/LinkedList; L0 L2 0
    // signature Lmodbat/bes/linkedlist/LinkedList<TE;>;
    // declaration: this extends modbat.bes.linkedlist.LinkedList<E>
    LOCALVARIABLE e Ljava/lang/Object; L0 L2 1
    // signature TE;
    // declaration: e extends E
    MAXSTACK = 2
    MAXLOCALS = 2

  // access flags 0x1
  // signature (TE;)Z
  // declaration: boolean offerLast(E)
  public offerLast(Ljava/lang/Object;)Z
   L0
    LINENUMBER 729 L0
    ALOAD 0
    ALOAD 1
    INVOKEVIRTUAL modbat/bes/linkedlist/LinkedList.addLast (Ljava/lang/Object;)V
   L1
    LINENUMBER 730 L1
    ICONST_1
    IRETURN
   L2
    LOCALVARIABLE this Lmodbat/bes/linkedlist/LinkedList; L0 L2 0
    // signature Lmodbat/bes/linkedlist/LinkedList<TE;>;
    // declaration: this extends modbat.bes.linkedlist.LinkedList<E>
    LOCALVARIABLE e Ljava/lang/Object; L0 L2 1
    // signature TE;
    // declaration: e extends E
    MAXSTACK = 2
    MAXLOCALS = 2

  // access flags 0x1
  // signature ()TE;
  // declaration: E peekFirst()
  public peekFirst()Ljava/lang/Object;
   L0
    LINENUMBER 742 L0
    ALOAD 0
    GETFIELD modbat/bes/linkedlist/LinkedList.first : Lmodbat/bes/linkedlist/LinkedList$Node;
    ASTORE 1
   L1
    LINENUMBER 743 L1
    ALOAD 1
    IFNONNULL L2
    ACONST_NULL
    GOTO L3
   L2
   FRAME FULL [modbat/bes/linkedlist/LinkedList modbat/bes/linkedlist/LinkedList$Node] []
    ALOAD 1
    GETFIELD modbat/bes/linkedlist/LinkedList$Node.item : Ljava/lang/Object;
   L3
   FRAME FULL [modbat/bes/linkedlist/LinkedList modbat/bes/linkedlist/LinkedList$Node] [java/lang/Object]
    ARETURN
   L4
    LOCALVARIABLE this Lmodbat/bes/linkedlist/LinkedList; L0 L4 0
    // signature Lmodbat/bes/linkedlist/LinkedList<TE;>;
    // declaration: this extends modbat.bes.linkedlist.LinkedList<E>
    LOCALVARIABLE f Lmodbat/bes/linkedlist/LinkedList$Node; L1 L4 1
    // signature Lmodbat/bes/linkedlist/LinkedList$Node<TE;>;
    // declaration: f extends modbat.bes.linkedlist.LinkedList$Node<E>
    MAXSTACK = 1
    MAXLOCALS = 2

  // access flags 0x1
  // signature ()TE;
  // declaration: E peekLast()
  public peekLast()Ljava/lang/Object;
   L0
    LINENUMBER 755 L0
    ALOAD 0
    GETFIELD modbat/bes/linkedlist/LinkedList.last : Lmodbat/bes/linkedlist/LinkedList$Node;
    ASTORE 1
   L1
    LINENUMBER 756 L1
    ALOAD 1
    IFNONNULL L2
    ACONST_NULL
    GOTO L3
   L2
   FRAME FULL [modbat/bes/linkedlist/LinkedList modbat/bes/linkedlist/LinkedList$Node] []
    ALOAD 1
    GETFIELD modbat/bes/linkedlist/LinkedList$Node.item : Ljava/lang/Object;
   L3
   FRAME FULL [modbat/bes/linkedlist/LinkedList modbat/bes/linkedlist/LinkedList$Node] [java/lang/Object]
    ARETURN
   L4
    LOCALVARIABLE this Lmodbat/bes/linkedlist/LinkedList; L0 L4 0
    // signature Lmodbat/bes/linkedlist/LinkedList<TE;>;
    // declaration: this extends modbat.bes.linkedlist.LinkedList<E>
    LOCALVARIABLE l Lmodbat/bes/linkedlist/LinkedList$Node; L1 L4 1
    // signature Lmodbat/bes/linkedlist/LinkedList$Node<TE;>;
    // declaration: l extends modbat.bes.linkedlist.LinkedList$Node<E>
    MAXSTACK = 1
    MAXLOCALS = 2

  // access flags 0x1
  // signature ()TE;
  // declaration: E pollFirst()
  public pollFirst()Ljava/lang/Object;
   L0
    LINENUMBER 768 L0
    ALOAD 0
    GETFIELD modbat/bes/linkedlist/LinkedList.first : Lmodbat/bes/linkedlist/LinkedList$Node;
    ASTORE 1
   L1
    LINENUMBER 769 L1
    ALOAD 1
    IFNONNULL L2
    ACONST_NULL
    GOTO L3
   L2
   FRAME FULL [modbat/bes/linkedlist/LinkedList modbat/bes/linkedlist/LinkedList$Node] []
    ALOAD 0
    ALOAD 1
    INVOKEVIRTUAL modbat/bes/linkedlist/LinkedList.unlinkFirst (Lmodbat/bes/linkedlist/LinkedList$Node;)Ljava/lang/Object;
   L3
   FRAME FULL [modbat/bes/linkedlist/LinkedList modbat/bes/linkedlist/LinkedList$Node] [java/lang/Object]
    ARETURN
   L4
    LOCALVARIABLE this Lmodbat/bes/linkedlist/LinkedList; L0 L4 0
    // signature Lmodbat/bes/linkedlist/LinkedList<TE;>;
    // declaration: this extends modbat.bes.linkedlist.LinkedList<E>
    LOCALVARIABLE f Lmodbat/bes/linkedlist/LinkedList$Node; L1 L4 1
    // signature Lmodbat/bes/linkedlist/LinkedList$Node<TE;>;
    // declaration: f extends modbat.bes.linkedlist.LinkedList$Node<E>
    MAXSTACK = 2
    MAXLOCALS = 2

  // access flags 0x1
  // signature ()TE;
  // declaration: E pollLast()
  public pollLast()Ljava/lang/Object;
   L0
    LINENUMBER 781 L0
    ALOAD 0
    GETFIELD modbat/bes/linkedlist/LinkedList.last : Lmodbat/bes/linkedlist/LinkedList$Node;
    ASTORE 1
   L1
    LINENUMBER 782 L1
    ALOAD 1
    IFNONNULL L2
    ACONST_NULL
    GOTO L3
   L2
   FRAME FULL [modbat/bes/linkedlist/LinkedList modbat/bes/linkedlist/LinkedList$Node] []
    ALOAD 0
    ALOAD 1
    INVOKEVIRTUAL modbat/bes/linkedlist/LinkedList.unlinkLast (Lmodbat/bes/linkedlist/LinkedList$Node;)Ljava/lang/Object;
   L3
   FRAME FULL [modbat/bes/linkedlist/LinkedList modbat/bes/linkedlist/LinkedList$Node] [java/lang/Object]
    ARETURN
   L4
    LOCALVARIABLE this Lmodbat/bes/linkedlist/LinkedList; L0 L4 0
    // signature Lmodbat/bes/linkedlist/LinkedList<TE;>;
    // declaration: this extends modbat.bes.linkedlist.LinkedList<E>
    LOCALVARIABLE l Lmodbat/bes/linkedlist/LinkedList$Node; L1 L4 1
    // signature Lmodbat/bes/linkedlist/LinkedList$Node<TE;>;
    // declaration: l extends modbat.bes.linkedlist.LinkedList$Node<E>
    MAXSTACK = 2
    MAXLOCALS = 2

  // access flags 0x1
  // signature (TE;)V
  // declaration: void push(E)
  public push(Ljava/lang/Object;)V
   L0
    LINENUMBER 795 L0
    ALOAD 0
    ALOAD 1
    INVOKEVIRTUAL modbat/bes/linkedlist/LinkedList.addFirst (Ljava/lang/Object;)V
   L1
    LINENUMBER 796 L1
    RETURN
   L2
    LOCALVARIABLE this Lmodbat/bes/linkedlist/LinkedList; L0 L2 0
    // signature Lmodbat/bes/linkedlist/LinkedList<TE;>;
    // declaration: this extends modbat.bes.linkedlist.LinkedList<E>
    LOCALVARIABLE e Ljava/lang/Object; L0 L2 1
    // signature TE;
    // declaration: e extends E
    MAXSTACK = 2
    MAXLOCALS = 2

  // access flags 0x1
  // signature ()TE;
  // declaration: E pop()
  public pop()Ljava/lang/Object;
   L0
    LINENUMBER 810 L0
    ALOAD 0
    INVOKEVIRTUAL modbat/bes/linkedlist/LinkedList.removeFirst ()Ljava/lang/Object;
    ARETURN
   L1
    LOCALVARIABLE this Lmodbat/bes/linkedlist/LinkedList; L0 L1 0
    // signature Lmodbat/bes/linkedlist/LinkedList<TE;>;
    // declaration: this extends modbat.bes.linkedlist.LinkedList<E>
    MAXSTACK = 1
    MAXLOCALS = 1

  // access flags 0x1
  public removeFirstOccurrence(Ljava/lang/Object;)Z
   L0
    LINENUMBER 823 L0
    ALOAD 0
    ALOAD 1
    INVOKEVIRTUAL modbat/bes/linkedlist/LinkedList.remove (Ljava/lang/Object;)Z
    IRETURN
   L1
    LOCALVARIABLE this Lmodbat/bes/linkedlist/LinkedList; L0 L1 0
    // signature Lmodbat/bes/linkedlist/LinkedList<TE;>;
    // declaration: this extends modbat.bes.linkedlist.LinkedList<E>
    LOCALVARIABLE o Ljava/lang/Object; L0 L1 1
    MAXSTACK = 2
    MAXLOCALS = 2

  // access flags 0x1
  public removeLastOccurrence(Ljava/lang/Object;)Z
   L0
    LINENUMBER 836 L0
    ALOAD 1
    IFNONNULL L1
   L2
    LINENUMBER 837 L2
    ALOAD 0
    GETFIELD modbat/bes/linkedlist/LinkedList.last : Lmodbat/bes/linkedlist/LinkedList$Node;
    ASTORE 2
   L3
   FRAME FULL [modbat/bes/linkedlist/LinkedList java/lang/Object modbat/bes/linkedlist/LinkedList$Node] []
    ALOAD 2
    IFNULL L4
   L5
    LINENUMBER 838 L5
    ALOAD 2
    GETFIELD modbat/bes/linkedlist/LinkedList$Node.item : Ljava/lang/Object;
    IFNONNULL L6
   L7
    LINENUMBER 839 L7
    ALOAD 0
    ALOAD 2
    INVOKEVIRTUAL modbat/bes/linkedlist/LinkedList.unlink (Lmodbat/bes/linkedlist/LinkedList$Node;)Ljava/lang/Object;
    POP
   L8
    LINENUMBER 840 L8
    ICONST_1
    IRETURN
   L6
    LINENUMBER 837 L6
   FRAME FULL [modbat/bes/linkedlist/LinkedList java/lang/Object modbat/bes/linkedlist/LinkedList$Node] []
    ALOAD 2
    GETFIELD modbat/bes/linkedlist/LinkedList$Node.prev : Lmodbat/bes/linkedlist/LinkedList$Node;
    ASTORE 2
    GOTO L3
   L4
   FRAME FULL [modbat/bes/linkedlist/LinkedList java/lang/Object modbat/bes/linkedlist/LinkedList$Node] []
    GOTO L9
   L1
    LINENUMBER 844 L1
   FRAME FULL [modbat/bes/linkedlist/LinkedList java/lang/Object] []
    ALOAD 0
    GETFIELD modbat/bes/linkedlist/LinkedList.last : Lmodbat/bes/linkedlist/LinkedList$Node;
    ASTORE 2
   L10
   FRAME FULL [modbat/bes/linkedlist/LinkedList java/lang/Object modbat/bes/linkedlist/LinkedList$Node] []
    ALOAD 2
    IFNULL L9
   L11
    LINENUMBER 845 L11
    ALOAD 1
    ALOAD 2
    GETFIELD modbat/bes/linkedlist/LinkedList$Node.item : Ljava/lang/Object;
    INVOKEVIRTUAL java/lang/Object.equals (Ljava/lang/Object;)Z
    IFEQ L12
   L13
    LINENUMBER 846 L13
    ALOAD 0
    ALOAD 2
    INVOKEVIRTUAL modbat/bes/linkedlist/LinkedList.unlink (Lmodbat/bes/linkedlist/LinkedList$Node;)Ljava/lang/Object;
    POP
   L14
    LINENUMBER 847 L14
    ICONST_1
    IRETURN
   L12
    LINENUMBER 844 L12
   FRAME FULL [modbat/bes/linkedlist/LinkedList java/lang/Object modbat/bes/linkedlist/LinkedList$Node] []
    ALOAD 2
    GETFIELD modbat/bes/linkedlist/LinkedList$Node.prev : Lmodbat/bes/linkedlist/LinkedList$Node;
    ASTORE 2
    GOTO L10
   L9
    LINENUMBER 851 L9
   FRAME FULL [modbat/bes/linkedlist/LinkedList java/lang/Object modbat/bes/linkedlist/LinkedList$Node] []
    ICONST_0
    IRETURN
   L15
    LOCALVARIABLE x Lmodbat/bes/linkedlist/LinkedList$Node; L3 L4 2
    // signature Lmodbat/bes/linkedlist/LinkedList$Node<TE;>;
    // declaration: x extends modbat.bes.linkedlist.LinkedList$Node<E>
    LOCALVARIABLE x Lmodbat/bes/linkedlist/LinkedList$Node; L10 L9 2
    // signature Lmodbat/bes/linkedlist/LinkedList$Node<TE;>;
    // declaration: x extends modbat.bes.linkedlist.LinkedList$Node<E>
    LOCALVARIABLE this Lmodbat/bes/linkedlist/LinkedList; L0 L15 0
    // signature Lmodbat/bes/linkedlist/LinkedList<TE;>;
    // declaration: this extends modbat.bes.linkedlist.LinkedList<E>
    LOCALVARIABLE o Ljava/lang/Object; L0 L15 1
    MAXSTACK = 2
    MAXLOCALS = 3

  // access flags 0x1
  // signature (I)Ljava/util/ListIterator<TE;>;
  // declaration: java.util.ListIterator<E> listIterator(int)
  public listIterator(I)Ljava/util/ListIterator;
   L0
    LINENUMBER 876 L0
    ALOAD 0
    ILOAD 1
    INVOKEVIRTUAL modbat/bes/linkedlist/LinkedList.checkPositionIndex (I)V
   L1
    LINENUMBER 877 L1
    NEW modbat/bes/linkedlist/LinkedList$ListItr
    DUP
    ALOAD 0
    ILOAD 1
    INVOKESPECIAL modbat/bes/linkedlist/LinkedList$ListItr.<init> (Lmodbat/bes/linkedlist/LinkedList;I)V
    ARETURN
   L2
    LOCALVARIABLE this Lmodbat/bes/linkedlist/LinkedList; L0 L2 0
    // signature Lmodbat/bes/linkedlist/LinkedList<TE;>;
    // declaration: this extends modbat.bes.linkedlist.LinkedList<E>
    LOCALVARIABLE index I L0 L2 1
    MAXSTACK = 4
    MAXLOCALS = 2

  // access flags 0x1
  // signature ()Ljava/util/Iterator<TE;>;
  // declaration: java.util.Iterator<E> descendingIterator()
  public descendingIterator()Ljava/util/Iterator;
   L0
    LINENUMBER 984 L0
    NEW modbat/bes/linkedlist/LinkedList$DescendingIterator
    DUP
    ALOAD 0
    INVOKESPECIAL modbat/bes/linkedlist/LinkedList$DescendingIterator.<init> (Lmodbat/bes/linkedlist/LinkedList;)V
    ARETURN
   L1
    LOCALVARIABLE this Lmodbat/bes/linkedlist/LinkedList; L0 L1 0
    // signature Lmodbat/bes/linkedlist/LinkedList<TE;>;
    // declaration: this extends modbat.bes.linkedlist.LinkedList<E>
    MAXSTACK = 3
    MAXLOCALS = 1

  // access flags 0x2
  // signature ()Lmodbat/bes/linkedlist/LinkedList<TE;>;
  // declaration: modbat.bes.linkedlist.LinkedList<E> superClone()
  private superClone()Lmodbat/bes/linkedlist/LinkedList;
    TRYCATCHBLOCK L0 L1 L2 java/lang/CloneNotSupportedException
   L0
    LINENUMBER 1006 L0
    ALOAD 0
    INVOKESPECIAL java/lang/Object.clone ()Ljava/lang/Object;
    CHECKCAST modbat/bes/linkedlist/LinkedList
   L1
    ARETURN
   L2
    LINENUMBER 1007 L2
   FRAME FULL [modbat/bes/linkedlist/LinkedList] [java/lang/CloneNotSupportedException]
    ASTORE 1
   L3
    LINENUMBER 1008 L3
    NEW java/lang/InternalError
    DUP
    INVOKESPECIAL java/lang/InternalError.<init> ()V
    ATHROW
   L4
    LOCALVARIABLE e Ljava/lang/CloneNotSupportedException; L3 L4 1
    LOCALVARIABLE this Lmodbat/bes/linkedlist/LinkedList; L0 L4 0
    // signature Lmodbat/bes/linkedlist/LinkedList<TE;>;
    // declaration: this extends modbat.bes.linkedlist.LinkedList<E>
    MAXSTACK = 2
    MAXLOCALS = 2

  // access flags 0x1
  public clone()Ljava/lang/Object;
   L0
    LINENUMBER 1019 L0
    ALOAD 0
    INVOKEVIRTUAL modbat/bes/linkedlist/LinkedList.superClone ()Lmodbat/bes/linkedlist/LinkedList;
    ASTORE 1
   L1
    LINENUMBER 1022 L1
    ALOAD 1
    ALOAD 1
    ACONST_NULL
    DUP_X1
    PUTFIELD modbat/bes/linkedlist/LinkedList.last : Lmodbat/bes/linkedlist/LinkedList$Node;
    PUTFIELD modbat/bes/linkedlist/LinkedList.first : Lmodbat/bes/linkedlist/LinkedList$Node;
   L2
    LINENUMBER 1023 L2
    ALOAD 1
    ICONST_0
    PUTFIELD modbat/bes/linkedlist/LinkedList.size : I
   L3
    LINENUMBER 1024 L3
    ALOAD 1
    ICONST_0
    PUTFIELD modbat/bes/linkedlist/LinkedList.modCount : I
   L4
    LINENUMBER 1027 L4
    ALOAD 0
    GETFIELD modbat/bes/linkedlist/LinkedList.first : Lmodbat/bes/linkedlist/LinkedList$Node;
    ASTORE 2
   L5
   FRAME FULL [modbat/bes/linkedlist/LinkedList modbat/bes/linkedlist/LinkedList modbat/bes/linkedlist/LinkedList$Node] []
    ALOAD 2
    IFNULL L6
   L7
    LINENUMBER 1028 L7
    ALOAD 1
    ALOAD 2
    GETFIELD modbat/bes/linkedlist/LinkedList$Node.item : Ljava/lang/Object;
    INVOKEVIRTUAL modbat/bes/linkedlist/LinkedList.add (Ljava/lang/Object;)Z
    POP
   L8
    LINENUMBER 1027 L8
    ALOAD 2
    GETFIELD modbat/bes/linkedlist/LinkedList$Node.next : Lmodbat/bes/linkedlist/LinkedList$Node;
    ASTORE 2
    GOTO L5
   L6
    LINENUMBER 1030 L6
   FRAME FULL [modbat/bes/linkedlist/LinkedList modbat/bes/linkedlist/LinkedList modbat/bes/linkedlist/LinkedList$Node] []
    ALOAD 1
    ARETURN
   L9
    LOCALVARIABLE x Lmodbat/bes/linkedlist/LinkedList$Node; L5 L6 2
    // signature Lmodbat/bes/linkedlist/LinkedList$Node<TE;>;
    // declaration: x extends modbat.bes.linkedlist.LinkedList$Node<E>
    LOCALVARIABLE this Lmodbat/bes/linkedlist/LinkedList; L0 L9 0
    // signature Lmodbat/bes/linkedlist/LinkedList<TE;>;
    // declaration: this extends modbat.bes.linkedlist.LinkedList<E>
    LOCALVARIABLE clone Lmodbat/bes/linkedlist/LinkedList; L1 L9 1
    // signature Lmodbat/bes/linkedlist/LinkedList<TE;>;
    // declaration: clone extends modbat.bes.linkedlist.LinkedList<E>
    MAXSTACK = 4
    MAXLOCALS = 3

  // access flags 0x1
  public toArray()[Ljava/lang/Object;
   L0
    LINENUMBER 1048 L0
    ALOAD 0
    GETFIELD modbat/bes/linkedlist/LinkedList.size : I
    ANEWARRAY java/lang/Object
    ASTORE 1
   L1
    LINENUMBER 1049 L1
    ICONST_0
    ISTORE 2
   L2
    LINENUMBER 1050 L2
    ALOAD 0
    GETFIELD modbat/bes/linkedlist/LinkedList.first : Lmodbat/bes/linkedlist/LinkedList$Node;
    ASTORE 3
   L3
   FRAME FULL [modbat/bes/linkedlist/LinkedList [Ljava/lang/Object; I modbat/bes/linkedlist/LinkedList$Node] []
    ALOAD 3
    IFNULL L4
   L5
    LINENUMBER 1051 L5
    ALOAD 1
    ILOAD 2
    IINC 2 1
    ALOAD 3
    GETFIELD modbat/bes/linkedlist/LinkedList$Node.item : Ljava/lang/Object;
    AASTORE
   L6
    LINENUMBER 1050 L6
    ALOAD 3
    GETFIELD modbat/bes/linkedlist/LinkedList$Node.next : Lmodbat/bes/linkedlist/LinkedList$Node;
    ASTORE 3
    GOTO L3
   L4
    LINENUMBER 1052 L4
   FRAME FULL [modbat/bes/linkedlist/LinkedList [Ljava/lang/Object; I modbat/bes/linkedlist/LinkedList$Node] []
    ALOAD 1
    ARETURN
   L7
    LOCALVARIABLE x Lmodbat/bes/linkedlist/LinkedList$Node; L3 L4 3
    // signature Lmodbat/bes/linkedlist/LinkedList$Node<TE;>;
    // declaration: x extends modbat.bes.linkedlist.LinkedList$Node<E>
    LOCALVARIABLE this Lmodbat/bes/linkedlist/LinkedList; L0 L7 0
    // signature Lmodbat/bes/linkedlist/LinkedList<TE;>;
    // declaration: this extends modbat.bes.linkedlist.LinkedList<E>
    LOCALVARIABLE result [Ljava/lang/Object; L1 L7 1
    LOCALVARIABLE i I L2 L7 2
    MAXSTACK = 3
    MAXLOCALS = 4

  // access flags 0x1
  // signature <T:Ljava/lang/Object;>([TT;)[TT;
  // declaration: T[] toArray<T>(T[])
  public toArray([Ljava/lang/Object;)[Ljava/lang/Object;
   L0
    LINENUMBER 1095 L0
    ALOAD 1
    ARRAYLENGTH
    ALOAD 0
    GETFIELD modbat/bes/linkedlist/LinkedList.size : I
    IF_ICMPGE L1
   L2
    LINENUMBER 1096 L2
    ALOAD 1
   L3
    LINENUMBER 1097 L3
    INVOKEVIRTUAL java/lang/Object.getClass ()Ljava/lang/Class;
    INVOKEVIRTUAL java/lang/Class.getComponentType ()Ljava/lang/Class;
    ALOAD 0
    GETFIELD modbat/bes/linkedlist/LinkedList.size : I
   L4
    LINENUMBER 1096 L4
    INVOKESTATIC java/lang/reflect/Array.newInstance (Ljava/lang/Class;I)Ljava/lang/Object;
    CHECKCAST [Ljava/lang/Object;
    ASTORE 1
   L1
    LINENUMBER 1098 L1
   FRAME FULL [modbat/bes/linkedlist/LinkedList [Ljava/lang/Object;] []
    ICONST_0
    ISTORE 2
   L5
    LINENUMBER 1099 L5
    ALOAD 1
    ASTORE 3
   L6
    LINENUMBER 1100 L6
    ALOAD 0
    GETFIELD modbat/bes/linkedlist/LinkedList.first : Lmodbat/bes/linkedlist/LinkedList$Node;
    ASTORE 4
   L7
   FRAME FULL [modbat/bes/linkedlist/LinkedList [Ljava/lang/Object; I [Ljava/lang/Object; modbat/bes/linkedlist/LinkedList$Node] []
    ALOAD 4
    IFNULL L8
   L9
    LINENUMBER 1101 L9
    ALOAD 3
    ILOAD 2
    IINC 2 1
    ALOAD 4
    GETFIELD modbat/bes/linkedlist/LinkedList$Node.item : Ljava/lang/Object;
    AASTORE
   L10
    LINENUMBER 1100 L10
    ALOAD 4
    GETFIELD modbat/bes/linkedlist/LinkedList$Node.next : Lmodbat/bes/linkedlist/LinkedList$Node;
    ASTORE 4
    GOTO L7
   L8
    LINENUMBER 1103 L8
   FRAME FULL [modbat/bes/linkedlist/LinkedList [Ljava/lang/Object; I [Ljava/lang/Object; modbat/bes/linkedlist/LinkedList$Node] []
    ALOAD 1
    ARRAYLENGTH
    ALOAD 0
    GETFIELD modbat/bes/linkedlist/LinkedList.size : I
    IF_ICMPLE L11
   L12
    LINENUMBER 1104 L12
    ALOAD 1
    ALOAD 0
    GETFIELD modbat/bes/linkedlist/LinkedList.size : I
    ACONST_NULL
    AASTORE
   L11
    LINENUMBER 1106 L11
   FRAME FULL [modbat/bes/linkedlist/LinkedList [Ljava/lang/Object; I [Ljava/lang/Object; modbat/bes/linkedlist/LinkedList$Node] []
    ALOAD 1
    ARETURN
   L13
    LOCALVARIABLE x Lmodbat/bes/linkedlist/LinkedList$Node; L7 L8 4
    // signature Lmodbat/bes/linkedlist/LinkedList$Node<TE;>;
    // declaration: x extends modbat.bes.linkedlist.LinkedList$Node<E>
    LOCALVARIABLE this Lmodbat/bes/linkedlist/LinkedList; L0 L13 0
    // signature Lmodbat/bes/linkedlist/LinkedList<TE;>;
    // declaration: this extends modbat.bes.linkedlist.LinkedList<E>
    LOCALVARIABLE a [Ljava/lang/Object; L0 L13 1
    // signature [TT;
    // declaration: a extends T[]
    LOCALVARIABLE i I L5 L13 2
    LOCALVARIABLE result [Ljava/lang/Object; L6 L13 3
    MAXSTACK = 3
    MAXLOCALS = 5

  // access flags 0x2
  private writeObject(Ljava/io/ObjectOutputStream;)V throws java/io/IOException 
   L0
    LINENUMBER 1122 L0
    ALOAD 1
    INVOKEVIRTUAL java/io/ObjectOutputStream.defaultWriteObject ()V
   L1
    LINENUMBER 1125 L1
    ALOAD 1
    ALOAD 0
    GETFIELD modbat/bes/linkedlist/LinkedList.size : I
    INVOKEVIRTUAL java/io/ObjectOutputStream.writeInt (I)V
   L2
    LINENUMBER 1128 L2
    ALOAD 0
    GETFIELD modbat/bes/linkedlist/LinkedList.first : Lmodbat/bes/linkedlist/LinkedList$Node;
    ASTORE 2
   L3
   FRAME FULL [modbat/bes/linkedlist/LinkedList java/io/ObjectOutputStream modbat/bes/linkedlist/LinkedList$Node] []
    ALOAD 2
    IFNULL L4
   L5
    LINENUMBER 1129 L5
    ALOAD 1
    ALOAD 2
    GETFIELD modbat/bes/linkedlist/LinkedList$Node.item : Ljava/lang/Object;
    INVOKEVIRTUAL java/io/ObjectOutputStream.writeObject (Ljava/lang/Object;)V
   L6
    LINENUMBER 1128 L6
    ALOAD 2
    GETFIELD modbat/bes/linkedlist/LinkedList$Node.next : Lmodbat/bes/linkedlist/LinkedList$Node;
    ASTORE 2
    GOTO L3
   L4
    LINENUMBER 1130 L4
   FRAME FULL [modbat/bes/linkedlist/LinkedList java/io/ObjectOutputStream modbat/bes/linkedlist/LinkedList$Node] []
    RETURN
   L7
    LOCALVARIABLE x Lmodbat/bes/linkedlist/LinkedList$Node; L3 L4 2
    // signature Lmodbat/bes/linkedlist/LinkedList$Node<TE;>;
    // declaration: x extends modbat.bes.linkedlist.LinkedList$Node<E>
    LOCALVARIABLE this Lmodbat/bes/linkedlist/LinkedList; L0 L7 0
    // signature Lmodbat/bes/linkedlist/LinkedList<TE;>;
    // declaration: this extends modbat.bes.linkedlist.LinkedList<E>
    LOCALVARIABLE s Ljava/io/ObjectOutputStream; L0 L7 1
    MAXSTACK = 2
    MAXLOCALS = 3

  // access flags 0x2
  private readObject(Ljava/io/ObjectInputStream;)V throws java/io/IOException java/lang/ClassNotFoundException 
   L0
    LINENUMBER 1140 L0
    ALOAD 1
    INVOKEVIRTUAL java/io/ObjectInputStream.defaultReadObject ()V
   L1
    LINENUMBER 1143 L1
    ALOAD 1
    INVOKEVIRTUAL java/io/ObjectInputStream.readInt ()I
    ISTORE 2
   L2
    LINENUMBER 1146 L2
    ICONST_0
    ISTORE 3
   L3
   FRAME FULL [modbat/bes/linkedlist/LinkedList java/io/ObjectInputStream I I] []
    ILOAD 3
    ILOAD 2
    IF_ICMPGE L4
   L5
    LINENUMBER 1147 L5
    ALOAD 0
    ALOAD 1
    INVOKEVIRTUAL java/io/ObjectInputStream.readObject ()Ljava/lang/Object;
    INVOKEVIRTUAL modbat/bes/linkedlist/LinkedList.linkLast (Ljava/lang/Object;)V
   L6
    LINENUMBER 1146 L6
    IINC 3 1
    GOTO L3
   L4
    LINENUMBER 1148 L4
   FRAME FULL [modbat/bes/linkedlist/LinkedList java/io/ObjectInputStream I I] []
    RETURN
   L7
    LOCALVARIABLE i I L3 L4 3
    LOCALVARIABLE this Lmodbat/bes/linkedlist/LinkedList; L0 L7 0
    // signature Lmodbat/bes/linkedlist/LinkedList<TE;>;
    // declaration: this extends modbat.bes.linkedlist.LinkedList<E>
    LOCALVARIABLE s Ljava/io/ObjectInputStream; L0 L7 1
    LOCALVARIABLE size I L2 L7 2
    MAXSTACK = 2
    MAXLOCALS = 4

  // access flags 0x1008
  static synthetic access$000(Lmodbat/bes/linkedlist/LinkedList;)I
   L0
    LINENUMBER 92 L0
    ALOAD 0
    GETFIELD modbat/bes/linkedlist/LinkedList.modCount : I
    IRETURN
   L1
    LOCALVARIABLE x0 Lmodbat/bes/linkedlist/LinkedList; L0 L1 0
    MAXSTACK = 1
    MAXLOCALS = 1

  // access flags 0x1008
  static synthetic access$100(Lmodbat/bes/linkedlist/LinkedList;)I
   L0
    LINENUMBER 92 L0
    ALOAD 0
    GETFIELD modbat/bes/linkedlist/LinkedList.modCount : I
    IRETURN
   L1
    LOCALVARIABLE x0 Lmodbat/bes/linkedlist/LinkedList; L0 L1 0
    MAXSTACK = 1
    MAXLOCALS = 1
}

