// class version 55.0 (55)
// access flags 0x21
public class modbat/bes/ElevatorSystem {

  // compiled from: ElevatorSystem.java

  // access flags 0x2
  private Z doorOpened

  // access flags 0x2
  private I currentFloor

  // access flags 0x2
  private I openWarningCounter

  // access flags 0x2
  private I closeWarningCounter

  // access flags 0x2
  private Z warningHappen

  // access flags 0x1
  public <init>()V
   L0
    LINENUMBER 13 L0
    ALOAD 0
    INVOKESPECIAL java/lang/Object.<init> ()V
   L1
    LINENUMBER 6 L1
    ALOAD 0
    ICONST_0
    PUTFIELD modbat/bes/ElevatorSystem.doorOpened : Z
   L2
    LINENUMBER 7 L2
    ALOAD 0
    ICONST_0
    PUTFIELD modbat/bes/ElevatorSystem.currentFloor : I
   L3
    LINENUMBER 8 L3
    ALOAD 0
    ICONST_0
    PUTFIELD modbat/bes/ElevatorSystem.openWarningCounter : I
   L4
    LINENUMBER 9 L4
    ALOAD 0
    ICONST_0
    PUTFIELD modbat/bes/ElevatorSystem.closeWarningCounter : I
   L5
    LINENUMBER 10 L5
    ALOAD 0
    ICONST_0
    PUTFIELD modbat/bes/ElevatorSystem.warningHappen : Z
   L6
    LINENUMBER 13 L6
    RETURN
   L7
    LOCALVARIABLE this Lmodbat/bes/ElevatorSystem; L0 L7 0
    MAXSTACK = 2
    MAXLOCALS = 1

  // access flags 0x1
  public moveElevator(I)Z
   L0
    LINENUMBER 17 L0
    ALOAD 0
    ICONST_0
    PUTFIELD modbat/bes/ElevatorSystem.warningHappen : Z
   L1
    LINENUMBER 19 L1
    ALOAD 0
    GETFIELD modbat/bes/ElevatorSystem.doorOpened : Z
    IFNE L2
   L3
    LINENUMBER 20 L3
    ALOAD 0
    ILOAD 1
    PUTFIELD modbat/bes/ElevatorSystem.currentFloor : I
   L4
    LINENUMBER 21 L4
    ICONST_1
    POP
    ICONST_0
    IRETURN
   L2
    LINENUMBER 24 L2
   FRAME FULL [modbat/bes/ElevatorSystem I] []
    ICONST_0
    IRETURN
   L5
    LOCALVARIABLE this Lmodbat/bes/ElevatorSystem; L0 L5 0
    LOCALVARIABLE requestingFloor I L0 L5 1
    MAXSTACK = 2
    MAXLOCALS = 2

  // access flags 0x1
  public openDoor()V
   L0
    LINENUMBER 29 L0
    ALOAD 0
    ICONST_0
    PUTFIELD modbat/bes/ElevatorSystem.closeWarningCounter : I
   L1
    LINENUMBER 30 L1
    ALOAD 0
    ICONST_1
    PUTFIELD modbat/bes/ElevatorSystem.doorOpened : Z
   L2
    LINENUMBER 31 L2
    ALOAD 0
    DUP
    GETFIELD modbat/bes/ElevatorSystem.openWarningCounter : I
    ICONST_1
    IADD
    PUTFIELD modbat/bes/ElevatorSystem.openWarningCounter : I
   L3
    LINENUMBER 33 L3
    ALOAD 0
    GETFIELD modbat/bes/ElevatorSystem.openWarningCounter : I
    ICONST_5
    IF_ICMPLT L4
   L5
    LINENUMBER 34 L5
    ALOAD 0
    ICONST_1
    PUTFIELD modbat/bes/ElevatorSystem.warningHappen : Z
   L6
    LINENUMBER 35 L6
    GETSTATIC java/lang/System.out : Ljava/io/PrintStream;
    LDC "The door is OPENED. You pressed the same button 5 times"
    INVOKEVIRTUAL java/io/PrintStream.println (Ljava/lang/String;)V
   L4
    LINENUMBER 38 L4
   FRAME FULL [modbat/bes/ElevatorSystem] []
    ALOAD 0
    GETFIELD modbat/bes/ElevatorSystem.openWarningCounter : I
    ICONST_5
    IF_ICMPGE L7
    ALOAD 0
    GETFIELD modbat/bes/ElevatorSystem.closeWarningCounter : I
    ICONST_5
    IF_ICMPGE L7
   L8
    LINENUMBER 39 L8
    ALOAD 0
    ICONST_0
    PUTFIELD modbat/bes/ElevatorSystem.warningHappen : Z
   L7
    LINENUMBER 40 L7
   FRAME FULL [modbat/bes/ElevatorSystem] []
    RETURN
   L9
    LOCALVARIABLE this Lmodbat/bes/ElevatorSystem; L0 L9 0
    MAXSTACK = 3
    MAXLOCALS = 1

  // access flags 0x1
  public closeDoor()V
   L0
    LINENUMBER 44 L0
    ALOAD 0
    ICONST_0
    PUTFIELD modbat/bes/ElevatorSystem.openWarningCounter : I
   L1
    LINENUMBER 45 L1
    ALOAD 0
    ICONST_0
    PUTFIELD modbat/bes/ElevatorSystem.doorOpened : Z
   L2
    LINENUMBER 46 L2
    ALOAD 0
    DUP
    GETFIELD modbat/bes/ElevatorSystem.closeWarningCounter : I
    ICONST_1
    IADD
    PUTFIELD modbat/bes/ElevatorSystem.closeWarningCounter : I
   L3
    LINENUMBER 48 L3
    ALOAD 0
    GETFIELD modbat/bes/ElevatorSystem.closeWarningCounter : I
    ICONST_5
    IF_ICMPLT L4
   L5
    LINENUMBER 49 L5
    ALOAD 0
    ICONST_1
    PUTFIELD modbat/bes/ElevatorSystem.warningHappen : Z
   L6
    LINENUMBER 50 L6
    GETSTATIC java/lang/System.out : Ljava/io/PrintStream;
    LDC "The door is CLOSED. You pressed the same button 5 times"
    INVOKEVIRTUAL java/io/PrintStream.println (Ljava/lang/String;)V
   L4
    LINENUMBER 53 L4
   FRAME FULL [modbat/bes/ElevatorSystem] []
    ALOAD 0
    GETFIELD modbat/bes/ElevatorSystem.openWarningCounter : I
    ICONST_5
    IF_ICMPGE L7
    ALOAD 0
    GETFIELD modbat/bes/ElevatorSystem.closeWarningCounter : I
    ICONST_5
    IF_ICMPGE L7
   L8
    LINENUMBER 54 L8
    ALOAD 0
    ICONST_0
    PUTFIELD modbat/bes/ElevatorSystem.warningHappen : Z
   L7
    LINENUMBER 55 L7
   FRAME FULL [modbat/bes/ElevatorSystem] []
    RETURN
   L9
    LOCALVARIABLE this Lmodbat/bes/ElevatorSystem; L0 L9 0
    MAXSTACK = 3
    MAXLOCALS = 1

  // access flags 0x1
  public isDoorOpened()Z
   L0
    LINENUMBER 58 L0
    ALOAD 0
    GETFIELD modbat/bes/ElevatorSystem.doorOpened : Z
    IRETURN
   L1
    LOCALVARIABLE this Lmodbat/bes/ElevatorSystem; L0 L1 0
    MAXSTACK = 1
    MAXLOCALS = 1

  // access flags 0x1
  public getCurrentFloor()I
   L0
    LINENUMBER 62 L0
    ALOAD 0
    GETFIELD modbat/bes/ElevatorSystem.currentFloor : I
    IRETURN
   L1
    LOCALVARIABLE this Lmodbat/bes/ElevatorSystem; L0 L1 0
    MAXSTACK = 1
    MAXLOCALS = 1

  // access flags 0x1
  public isWarningHappen()Z
   L0
    LINENUMBER 66 L0
    ALOAD 0
    GETFIELD modbat/bes/ElevatorSystem.warningHappen : Z
    IRETURN
   L1
    LOCALVARIABLE this Lmodbat/bes/ElevatorSystem; L0 L1 0
    MAXSTACK = 1
    MAXLOCALS = 1

  // access flags 0x1
  public getOpenWarningCounter()I
   L0
    LINENUMBER 70 L0
    ALOAD 0
    GETFIELD modbat/bes/ElevatorSystem.openWarningCounter : I
    IRETURN
   L1
    LOCALVARIABLE this Lmodbat/bes/ElevatorSystem; L0 L1 0
    MAXSTACK = 1
    MAXLOCALS = 1

  // access flags 0x1
  public getCloseWarningCounter()I
   L0
    LINENUMBER 74 L0
    ALOAD 0
    GETFIELD modbat/bes/ElevatorSystem.closeWarningCounter : I
    IRETURN
   L1
    LOCALVARIABLE this Lmodbat/bes/ElevatorSystem; L0 L1 0
    MAXSTACK = 1
    MAXLOCALS = 1

  // access flags 0x9
  public static main([Ljava/lang/String;)V
   L0
    LINENUMBER 88 L0
    RETURN
   L1
    LOCALVARIABLE args [Ljava/lang/String; L0 L1 0
    MAXSTACK = 0
    MAXLOCALS = 1
}

